Workbook
Name AcquisitionCapRate: Analysis!$F$3
Name CostGrowth: Analysis!$B$9
Name ExitCapRate: Analysis!$F$7
Name HoldingPeriod: Analysis!$F$6
Name PurchasePrice: Analysis!$F$2
Name RentGrowth: Analysis!$B$10
Name SellPrice: Analysis!$F$8
Name StartingRent: Analysis!$F$19
Name Units: Analysis!$B$3

Sheet Analysis
A1: Asset Details | D1: Acquisition Details | H1: Profit Metrics
A2: Community Name | B2: West Ridge North | D2: Purchase Price | F2: =B46/AcquisitionCapRate -> 7288683.3 | H2: Total Investment | J2: =ABS(SUM(D51:E51)) -> 9288683.3
A3: Units | B3: 80 | D3: Cap Rate | F3: 0.06 | H3: Total Return | J3: =SUM(D53:N53)+J2 -> 79660391
A4: Year Built | B4: 1994 | H4: Return on Investment | J4: =J3/J2 -> 8.5760692
A5: Last Remodeled | B5: N/A | D5: Sale Details | H5: Benchmark Rate | J5: 0.2
A6: Seller | B6: Shady Tree Mgmt | D6: Holding Period (Years) | F6: 10 | H6: FV | J6: ='TVM Analysis'!C5 -> 57513079
D7: Exit Cap Rate | F7: 0.05 | H7: PV | J7: ='TVM Analysis'!G5 -> 12865598
A8: Operational Assumptions | D8: Sale Price | F8: =HLOOKUP(HoldingPeriod,D16:N46,31,0)/ExitCapRate -> 59099662 | H8: NPV | J8: =NPV(J5,E53:N53)+D53 -> 7391418.7
A9: Cost Growth % | B9: 0.02 | H9: XNPV | J9: =XNPV(J5,D53:N53,D15:N15) -> 7372046.7
A10: Rent Growth % | B10: 0.05 | H10: IRR | J10: =IRR(D53:N53) -> 0.29781515
H11: XIRR | J11: =XIRR(D53:N53,D15:N15) -> 0.2975477
A14: Cash Flow Analysis
D15: 45322 | E15: =EOMONTH(D15,12) -> 45688 | F15: =EOMONTH(E15,12) -> 46053 | G15: =EOMONTH(F15,12) -> 46418 | H15: =EOMONTH(G15,12) -> 46783 | I15: =EOMONTH(H15,12) -> 47149 | J15: =EOMONTH(I15,12) -> 47514 | K15: =EOMONTH(J15,12) -> 47879 | L15: =EOMONTH(K15,12) -> 48244 | ... N15: =EOMONTH(M15,12) -> 48975
B16: Last Year Financials | D16: 0 | E16: =D16+1 -> 1 | F16: =E16+1 -> 2 | G16: =F16+1 -> 3 | H16: =G16+1 -> 4 | I16: =H16+1 -> 5 | J16: =I16+1 -> 6 | K16: =J16+1 -> 7 | L16: =K16+1 -> 8 | ... N16: =M16+1 -> 10
A18: Net Potential Rent | B18: 1493760 | D18: 0 | E18: 0 | F18: =IF(HoldingPeriod<F16,0,F19*Units*12) -> 2208000 | G18: =IF(HoldingPeriod<G16,0,G19*Units*12) -> 2318400 | H18: =IF(HoldingPeriod<H16,0,H19*Units*12) -> 2434320 | I18: =IF(HoldingPeriod<I16,0,I19*Units*12) -> 2556036 | J18: =IF(HoldingPeriod<J16,0,J19*Units*12) -> 2683837.8 | K18: =IF(HoldingPeriod<K16,0,K19*Units*12) -> 2818029.7 | L18: =IF(HoldingPeriod<L16,0,L19*Units*12) -> 2958931.2 | M18: =IF(HoldingPeriod<M16,0,M19*Units*12) -> 3106877.7 | N18: =IF(HoldingPeriod<N16,0,N19*Units*12) -> 3262221.6
A19: Effective Monthly Rent / Unit | F19: 2300 | G19: =F19*(1+RentGrowth) -> 2415 | H19: =G19*(1+RentGrowth) -> 2535.75 | I19: =H19*(1+RentGrowth) -> 2662.5375 | J19: =I19*(1+RentGrowth) -> 2795.6644 | K19: =J19*(1+RentGrowth) -> 2935.4476 | L19: =K19*(1+RentGrowth) -> 3082.22 | M19: =L19*(1+RentGrowth) -> 3236.331 | N19: =M19*(1+RentGrowth) -> 3398.1475
A21: Vacancy | B21: -410784 | D21: =-D18*(1-D23) -> 0 | E21: =-E18*(1-E23) -> 0 | F21: =-F18*(1-F23) -> -552000 | G21: =-G18*(1-G23) -> -115920 | H21: =-H18*(1-H23) -> -121716 | I21: =-I18*(1-I23) -> -127801.8 | J21: =-J18*(1-J23) -> -134191.89 | K21: =-K18*(1-K23) -> -140901.48 | ... N21: =-N18*(1-N23) -> -163111.08
A22: Avg. Occupied Units | E22: 0 | F22: 60 | G22: 76 | H22: 76 | I22: 76 | J22: 76 | K22: 76 | L22: 76 | M22: 76 | N22: 76
A23: Avg. Occupancy | E23: =E22/Units -> 0 | F23: =F22/Units -> 0.75 | G23: =G22/Units -> 0.95 | H23: =H22/Units -> 0.95 | I23: =I22/Units -> 0.95 | J23: =J22/Units -> 0.95 | K23: =K22/Units -> 0.95 | L23: =L22/Units -> 0.95 | ... N23: =N22/Units -> 0.95
A25: Delinquency | B25: -179251 | D25: 0 | E25: =SUM(E21,E18)*E26 -> 0 | F25: =SUM(F21,F18)*F26 -> 99360 | G25: =SUM(G21,G18)*G26 -> 88099.2 | H25: =SUM(H21,H18)*H26 -> 92504.16 | I25: =SUM(I21,I18)*I26 -> 97129.368 | J25: =SUM(J21,J18)*J26 -> 101985.84 | K25: =SUM(K21,K18)*K26 -> 107085.13 | L25: =SUM(L21,L18)*L26 -> 112439.38 | ... N25: =SUM(N21,N18)*N26 -> 123964.42
A26: Delinquency % | E26: 0.12 | F26: 0.06 | G26: 0.04 | H26: 0.04 | I26: 0.04 | J26: 0.04 | K26: 0.04 | L26: 0.04 | M26: 0.04 | N26: 0.04
A28: Total Rental Income | B28: =SUM(B18,B21,B25) -> 903725 | D28: =SUM(D18,D21,D25) -> 0 | E28: =SUM(E18,E21,E25) -> 0 | F28: =SUM(F18,F21,F25) -> 1755360 | G28: =SUM(G18,G21,G25) -> 2290579.2 | H28: =SUM(H18,H21,H25) -> 2405108.2 | I28: =SUM(I18,I21,I25) -> 2525363.6 | J28: =SUM(J18,J21,J25) -> 2651631.7 | K28: =SUM(K18,K21,K25) -> 2784213.3 | ... N28: =SUM(N18,N21,N25) -> 3223075
A30: Repairs & Maintenance | B30: -58742 | D30: 0 | E30: =SUM(E$18+E$21)*E31 -> 0 | F30: =SUM(F18+F21)*F31 -> 82800 | G30: =SUM(G18+G21)*G31 -> 110124 | H30: =SUM(H18+H21)*H31 -> 115630.2 | I30: =SUM(I18+I21)*I31 -> 121411.71 | J30: =SUM(J18+J21)*J31 -> 127482.3 | K30: =SUM(K18+K21)*K31 -> 133856.41 | L30: =SUM(L18+L21)*L31 -> 140549.23 | M30: =SUM(M18+M21)*M31 -> 147576.69 | N30: =SUM(N18+N21)*N31 -> 154955.53
A31: R&M Ratio | E31: 0.05 | F31: 0.05 | G31: 0.05 | H31: 0.05 | I31: 0.05 | J31: 0.05 | K31: 0.05 | L31: 0.05 | M31: 0.05 | N31: 0.05
A33: Turn & Marketing Expenses | B33: -27111 | D33: 0 | E33: =SUM(E$18+E$21)*E34 -> 0 | F33: =SUM(F$18+F$21)*F34 -> 49680 | G33: =SUM(G$18+G$21)*G34 -> 66074.4 | H33: =SUM(H$18+H$21)*H34 -> 69378.12 | I33: =SUM(I$18+I$21)*I34 -> 72847.026 | J33: =SUM(J$18+J$21)*J34 -> 76489.377 | K33: =SUM(K$18+K$21)*K34 -> 80313.846 | L33: =SUM(L$18+L$21)*L34 -> 84329.538 | ... N33: =SUM(N$18+N$21)*N34 -> 92973.316
A34: Turn Ratio | E34: 0.03 | F34: 0.03 | G34: 0.03 | H34: 0.03 | I34: 0.03 | J34: 0.03 | K34: 0.03 | L34: 0.03 | M34: 0.03 | N34: 0.03
A36: Utilities (Vacancy) | B36: -7304 | D36: 0 | E36: =IF(HoldingPeriod<E16,0,(Units-E22)*E37) -> 24000 | F36: =IF(HoldingPeriod<F16,0,(Units-F22)*F37) -> 6120 | G36: =IF(HoldingPeriod<G16,0,(Units-G22)*G37) -> 1248.48 | H36: =IF(HoldingPeriod<H16,0,(Units-H22)*H37) -> 1273.4496 | I36: =IF(HoldingPeriod<I16,0,(Units-I22)*I37) -> 1298.9186 | J36: =IF(HoldingPeriod<J16,0,(Units-J22)*J37) -> 1324.897 | K36: =IF(HoldingPeriod<K16,0,(Units-K22)*K37) -> 1351.3949 | L36: =IF(HoldingPeriod<L16,0,(Units-L22)*L37) -> 1378.4228 | ... N36: =IF(HoldingPeriod<N16,0,(Units-N22)*N37) -> 1434.1111
A37: Avg. Utilities Cost / Vacant Unit | E37: 300 | F37: =E37*(1+CostGrowth) -> 306 | G37: =F37*(1+CostGrowth) -> 312.12 | H37: =G37*(1+CostGrowth) -> 318.3624 | I37: =H37*(1+CostGrowth) -> 324.72965 | J37: =I37*(1+CostGrowth) -> 331.22424 | K37: =J37*(1+CostGrowth) -> 337.84873 | L37: =K37*(1+CostGrowth) -> 344.6057 | M37: =L37*(1+CostGrowth) -> 351.49781 | N37: =M37*(1+CostGrowth) -> 358.52777
A39: Salaries and Wages | B39: -212582 | D39: 0 | E39: =IF(HoldingPeriod<E16,0,$B$39*(1+CostGrowth^E16)) -> -216833.64 | F39: =IF(HoldingPeriod<F16,0,$B$39*(1+CostGrowth^F16)) -> -212667.03 | G39: =IF(HoldingPeriod<G16,0,$B$39*(1+CostGrowth^G16)) -> -212583.7 | H39: =IF(HoldingPeriod<H16,0,$B$39*(1+CostGrowth^H16)) -> -212582.03 | I39: =IF(HoldingPeriod<I16,0,$B$39*(1+CostGrowth^I16)) -> -212582 | J39: =IF(HoldingPeriod<J16,0,$B$39*(1+CostGrowth^J16)) -> -212582 | K39: =IF(HoldingPeriod<K16,0,$B$39*(1+CostGrowth^K16)) -> -212582 | L39: =IF(HoldingPeriod<L16,0,$B$39*(1+CostGrowth^L16)) -> -212582 | ... N39: =IF(HoldingPeriod<N16,0,$B$39*(1+CostGrowth^N16)) -> -212582
A40: Taxes | B40: -160665 | D40: 0 | E40: =IF(HoldingPeriod<E16,0,-E41*E42) -> -255103.92 | F40: =IF(HoldingPeriod<F16,0,-F41*F42) -> -260206 | G40: =IF(HoldingPeriod<G16,0,-G41*G42) -> -265410.11 | H40: =IF(HoldingPeriod<H16,0,-H41*H42) -> -270718.32 | I40: =IF(HoldingPeriod<I16,0,-I41*I42) -> -276132.68 | J40: =IF(HoldingPeriod<J16,0,-J41*J42) -> -281655.34 | K40: =IF(HoldingPeriod<K16,0,-K41*K42) -> -287288.44 | L40: =IF(HoldingPeriod<L16,0,-L41*L42) -> -293034.21 | ... N40: =IF(HoldingPeriod<N16,0,-N41*N42) -> -304872.8
A41: Tax rate | E41: 0.035 | F41: 0.035 | G41: 0.035 | H41: 0.035 | I41: 0.035 | J41: 0.035 | K41: 0.035 | L41: 0.035 | M41: 0.035 | N41: 0.035
A42: Assessed value | E42: =-D48 -> 7288683.3 | F42: =E42*(1+CostGrowth) -> 7434457 | G42: =F42*(1+CostGrowth) -> 7583146.1 | H42: =G42*(1+CostGrowth) -> 7734809.1 | I42: =H42*(1+CostGrowth) -> 7889505.2 | J42: =I42*(1+CostGrowth) -> 8047295.3 | K42: =J42*(1+CostGrowth) -> 8208241.3 | L42: =K42*(1+CostGrowth) -> 8372406.1 | M42: =L42*(1+CostGrowth) -> 8539854.2 | N42: =M42*(1+CostGrowth) -> 8710651.3
A44: Total Operating Expenses | B44: =SUM(B30,B33,B36,B39,B40) -> -466404 | D44: =SUM(D30,D33,D36,D39,D40) -> 0 | E44: =SUM(E30,E33,E36,E39,E40) -> -447937.56 | F44: =SUM(F30,F33,F36,F39,F40) -> -334273.03 | G44: =SUM(G30,G33,G36,G39,G40) -> -300546.94 | H44: =SUM(H30,H33,H36,H39,H40) -> -297018.58 | I44: =SUM(I30,I33,I36,I39,I40) -> -293157.03 | J44: =SUM(J30,J33,J36,J39,J40) -> -288940.77 | K44: =SUM(K30,K33,K36,K39,K40) -> -284348.79 | ... N44: =SUM(N30,N33,N36,N39,N40) -> -268091.84
A46: Net Operating Income | B46: =SUM(B28,B44) -> 437321 | D46: =SUM(D28,D44) -> 0 | E46: =SUM(E28,E44) -> -447937.56 | F46: =SUM(F28,F44) -> 1421087 | G46: =SUM(G28,G44) -> 1990032.3 | H46: =SUM(H28,H44) -> 2108089.6 | I46: =SUM(I28,I44) -> 2232206.5 | J46: =SUM(J28,J44) -> 2362691 | K46: =SUM(K28,K44) -> 2499864.5 | ... N46: =SUM(N28,N44) -> 2954983.1
A48: Property (Purchase) Sale | B48: -1000 | D48: =-PurchasePrice -> -7288683.3 | E48: =IF(HoldingPeriod=E16,SellPrice,0) -> 0 | F48: =IF(HoldingPeriod=F16,SellPrice,0) -> 0 | G48: =IF(HoldingPeriod=G16,SellPrice,0) -> 0 | H48: =IF(HoldingPeriod=H16,SellPrice,0) -> 0 | I48: =IF(HoldingPeriod=I16,SellPrice,0) -> 0 | J48: =IF(HoldingPeriod=J16,SellPrice,0) -> 0 | K48: =IF(HoldingPeriod=K16,SellPrice,0) -> 0 | L48: =IF(HoldingPeriod=L16,SellPrice,0) -> 0 | ... N48: =IF(HoldingPeriod=N16,SellPrice,0) -> 59099662
A49: Renovations | B49: -20182 | D49: 0 | E49: =Units*-25000 -> -2000000 | F49: 0 | G49: 0 | H49: 0 | I49: 0 | J49: 0 | K49: 0 | L49: 0 | M49: 0 | N49: 0
A51: Total Capital Expenditures | B51: =SUM(B48:B49) -> -21182 | D51: =SUM(D48:D49) -> -7288683.3 | E51: =SUM(E48:E49) -> -2000000 | F51: =SUM(F48:F49) -> 0 | G51: =SUM(G48:G49) -> 0 | H51: =SUM(H48:H49) -> 0 | I51: =SUM(I48:I49) -> 0 | J51: =SUM(J48:J49) -> 0 | K51: =SUM(K48:K49) -> 0 | ... N51: =SUM(N48:N49) -> 59099662
A53: Net Income | B53: =SUM(B46,B51) -> 416139 | D53: =SUM(D46,D51) -> -7288683.3 | E53: =SUM(E46,E51) -> -2447937.6 | F53: =SUM(F46,F51) -> 1421087 | G53: =SUM(G46,G51) -> 1990032.3 | H53: =SUM(H46,H51) -> 2108089.6 | I53: =SUM(I46,I51) -> 2232206.5 | J53: =SUM(J46,J51) -> 2362691 | K53: =SUM(K46,K51) -> 2499864.5 | ... N53: =SUM(N46,N51) -> 62054646

Sheet TVM Analysis
A1: Future Value | E1: Present Value
A2: Benchmark Rate | C2: =Analysis!J5 -> 0.2 | E2: Benchmark Rate | G2: =Analysis!J5 -> 0.2
A3: Number of Periods | C3: =Analysis!F6 -> 10 | E3: Number of Periods | G3: =HoldingPeriod -> 10
A4: Present Value | C4: =Analysis!J2 -> 9288683.3 | E4: Future Value | G4: =Analysis!J3 -> 79660391
A5: Future Value | C5: =FV(C2,C3,,-C4) -> 57513079 | E5: Present Value | G5: =-PV(G2,G3,,G4) -> 12865598
