Workbook
Name checkInd: CheckSum!$A$103
Name CheckSumHigh: IFERROR(MMULT(TRANSPOSE(CS_Seq1),CS_TableHigh),0)
Name CheckSumLow: IFERROR(MMULT(TRANSPOSE(CS_Seq1),CS_TableLow),0)
Name CheckSumSortCity: IFERROR(SUMPRODUCT(CS_Seq1,CODE(CS_SortCity)),0)
Name CheckSumSortTemp: SUMPRODUCT(CS_SortTemp,CS_Seq1)
Name CS_Int: CheckSum!$A$2:$A$51
Name CS_Seq1: CheckSum!$B$2:$B$51
Name CS_SortCity: MonthSorted!$B$5:$B$54
Name CS_SortTemp: MonthSorted!$C$5:$C$54
Name CS_TableHigh: SummaryHigh!$D$5:$O$54
Name CS_TableLow: SummaryLow!$D$5:$O$54
Name ListCity: CheckSum!$D$2:$D$51
Name ListsMonthShort: CheckSum!$E$2:$P$2

Sheet CheckSum
A1: CS_Int | B1: CS_Seq1 | D1: ListCity | E1: ListMonthShort
A2: 1 | B2: 2 | D2: Atlanta | E2: Jan | F2: Feb | G2: Mar | H2: Apr | I2: May | J2: Jun | K2: Jul | L2: Aug | M2: Sep | N2: Oct | O2: Nov | P2: Dec
A3: 2 | B3: 3 | D3: Austin
A4: 3 | B4: 5 | D4: Baltimore
A5: 4 | B5: 7 | D5: Birmingham
A6: 5 | B6: 11 | D6: Boston
A7: 6 | B7: 13 | D7: Buffalo
A8: 7 | B8: 17 | D8: Charlotte
A9: 8 | B9: 19 | D9: Chicago
A10: 9 | B10: 23 | D10: Cincinnati
A11: 10 | B11: 29 | D11: Cleveland
A12: 11 | B12: 31 | D12: Columbus
A13: 12 | B13: 37 | D13: Dallas
A14: 13 | B14: 41 | D14: Denver
... A51: 50 | B51: 229 | D51: Virginia Beach

Sheet Introduction
H2: Excel Skills for Business: Advanced
H4: End of Course - Assignment
I6: Final Assignment

Sheet Part 1
A1: This sheet is intentionally blank

Sheet Data1
A1: Temperature Data
A2: Atlanta | B2: Georgia | C2: M1H52L34 | D2: M2H57L38 | E2: M3H65L44 | F2: M4H73L52 | G2: M5H8ØL6Ø | H2: M6H86L68 | I2: M7H89L71 | J2: M8H88L71 | K2: M9H82L65 | L2: M1ØH73L54 | M2: M11H64L45 | N2: M12H54L37
A3: Austin | B3: Texas | C3: M1H62L42 | D3: M2H65L45 | E3: M3H72L51 | F3: M4H8ØL59 | G3: M5H87L67 | H3: M6H92L72 | I3: M7H96L74 | J3: M8H97L75 | K3: M9H91L69 | L3: M1ØH82L61 | M3: M11H71L51 | N3: M12H63L42
A4: Baltimore | B4: Maryland | C4: M1H41L24 | D4: M2H45L27 | E4: M3H54L34 | F4: M4H65L43 | G4: M5H74L52 | H4: M6H83L62 | I4: M7H87L67 | J4: M8H85L65 | K4: M9H78L58 | L4: M1ØH67L45 | M4: M11H56L37 | N4: M12H45L28
A5: Birmingham | B5: Alabama | C5: M1H54L34 | D5: M2H58L37 | E5: M3H67L44 | F5: M4H74L51 | G5: M5H82L6Ø | H5: M6H88L68 | I5: M7H91L71 | J5: M8H91L71 | K5: M9H85L64 | L5: M1ØH75L53 | M5: M11H65L44 | N5: M12H56L36
A6: Boston | B6: Massachusetts | C6: M1H36L22 | D6: M2H39L25 | E6: M3H45L31 | F6: M4H56L41 | G6: M5H66L5Ø | H6: M6H76L6Ø | I6: M7H81L65 | J6: M8H8ØL65 | K6: M9H72L57 | L6: M1ØH61L47 | M6: M11H52L38 | N6: M12H41L28
A7: Buffalo | B7: New York | C7: M1H31L19 | D7: M2H33L19 | E7: M3H42L26 | F7: M4H55L37 | G7: M5H67L47 | H7: M6H75L57 | I7: M7H8ØL62 | J7: M8H78L61 | K7: M9H71L53 | L7: M1ØH59L43 | M7: M11H48L34 | N7: M12H36L24
A8: Charlotte | B8: North Carolina | C8: M1H51L3Ø | D8: M2H55L33 | E8: M3H63L39 | F8: M4H72L47 | G8: M5H79L56 | H8: M6H86L65 | I8: M7H89L68 | J8: M8H88L67 | K8: M9H81L6Ø | L8: M1ØH72L49 | M8: M11H62L39 | N8: M12H53L32
A9: Chicago | B9: Illinois | C9: M1H31L17 | D9: M2H35L2Ø | E9: M3H47L29 | F9: M4H59L39 | G9: M5H7ØL48 | H9: M6H8ØL58 | I9: M7H84L64 | J9: M8H82L63 | K9: M9H75L54 | L9: M1ØH62L43 | M9: M11H48L32 | N9: M12H35L21
A10: Cincinnati | B10: Ohio | C10: M1H4ØL22 | D10: M2H45L25 | E10: M3H55L33 | F10: M4H66L42 | G10: M5H75L52 | H10: M6H83L61 | I10: M7H87L65 | J10: M8H86L63 | K10: M9H79L55 | L10: M1ØH68L43 | M10: M11H56L34 | N10: M12H43L26
A11: Cleveland | B11: Ohio | C11: M1H34L22 | D11: M2H38L24 | E11: M3H47L3Ø | F11: M4H59L4Ø | G11: M5H7ØL5Ø | H11: M6H79L6Ø | I11: M7H83L64 | J11: M8H81L63 | K11: M9H74L56 | L11: M1ØH62L45 | M11: M11H51L37 | N11: M12H38L26
A12: Columbus | B12: Ohio | C12: M1H37L23 | D12: M2H41L25 | E12: M3H51L33 | F12: M4H64L43 | G12: M5H73L52 | H12: M6H82L62 | I12: M7H85L66 | J12: M8H84L64 | K12: M9H77L57 | L12: M1ØH65L45 | M12: M11H53L36 | N12: M12H4ØL27
A13: Dallas | B13: Texas | C13: M1H57L37 | D13: M2H61L41 | E13: M3H69L49 | F13: M4H77L56 | G13: M5H84L65 | H13: M6H92L73 | I13: M7H96L77 | J13: M8H96L77 | K13: M9H89L69 | L13: M1ØH79L58 | M13: M11H67L48 | N13: M12H58L39
... A51: Virginia Beach | B51: Virginia | C51: M1H48L33 | D51: M2H51L34 | E51: M3H58L41 | F51: M4H68L49 | G51: M5H75L58 | H51: M6H84L67 | I51: M7H87L72 | J51: M8H85L71 | K51: M9H79L65 | L51: M1ØH7ØL54 | M51: M11H61L45 | N51: M12H52L36

Sheet Workings_1

Sheet SummaryHigh
Q2: Jan
B3: Summary Table of High Temperatures - by Month
B4: City | C4: State | D4: {=ListsMonthShort} -> Jan | E4: Feb | F4: Mar | G4: Apr | H4: May | I4: Jun | J4: Jul | K4: Aug | L4: Sep | M4: Oct | N4: Nov | O4: Dec
B5: {=ListCity} -> Atlanta | C5: =VLOOKUP(B5,Data1!A2:B51,2,FALSE) -> Georgia | D5: =VALUE(SUBSTITUTE(MID(Data1!C2,FIND("H",Data1!C2)+1,FIND("L",Data1!C2)-FIND("H",Data1!C2)-1),"Ø","0")) -> 52 | E5: =VALUE(SUBSTITUTE(MID(Data1!D2,FIND("H",Data1!D2)+1,FIND("L",Data1!D2)-FIND("H",Data1!D2)-1),"Ø","0")) -> 57 | F5: =VALUE(SUBSTITUTE(MID(Data1!E2,FIND("H",Data1!E2)+1,FIND("L",Data1!E2)-FIND("H",Data1!E2)-1),"Ø","0")) -> 65 | G5: =VALUE(SUBSTITUTE(MID(Data1!F2,FIND("H",Data1!F2)+1,FIND("L",Data1!F2)-FIND("H",Data1!F2)-1),"Ø","0")) -> 73 | H5: =VALUE(SUBSTITUTE(MID(Data1!G2,FIND("H",Data1!G2)+1,FIND("L",Data1!G2)-FIND("H",Data1!G2)-1),"Ø","0")) -> 80 | I5: =VALUE(SUBSTITUTE(MID(Data1!H2,FIND("H",Data1!H2)+1,FIND("L",Data1!H2)-FIND("H",Data1!H2)-1),"Ø","0")) -> 86 | J5: =VALUE(SUBSTITUTE(MID(Data1!I2,FIND("H",Data1!I2)+1,FIND("L",Data1!I2)-FIND("H",Data1!I2)-1),"Ø","0")) -> 89 | K5: =VALUE(SUBSTITUTE(MID(Data1!J2,FIND("H",Data1!J2)+1,FIND("L",Data1!J2)-FIND("H",Data1!J2)-1),"Ø","0")) -> 88 | ... O5: =VALUE(SUBSTITUTE(MID(Data1!N2,FIND("H",Data1!N2)+1,FIND("L",Data1!N2)-FIND("H",Data1!N2)-1),"Ø","0")) -> 54
B6: Austin | C6: =VLOOKUP(B6,Data1!A3:B52,2,FALSE) -> Texas | D6: =VALUE(SUBSTITUTE(MID(Data1!C3,FIND("H",Data1!C3)+1,FIND("L",Data1!C3)-FIND("H",Data1!C3)-1),"Ø","0")) -> 62 | E6: =VALUE(SUBSTITUTE(MID(Data1!D3,FIND("H",Data1!D3)+1,FIND("L",Data1!D3)-FIND("H",Data1!D3)-1),"Ø","0")) -> 65 | F6: =VALUE(SUBSTITUTE(MID(Data1!E3,FIND("H",Data1!E3)+1,FIND("L",Data1!E3)-FIND("H",Data1!E3)-1),"Ø","0")) -> 72 | G6: =VALUE(SUBSTITUTE(MID(Data1!F3,FIND("H",Data1!F3)+1,FIND("L",Data1!F3)-FIND("H",Data1!F3)-1),"Ø","0")) -> 80 | H6: =VALUE(SUBSTITUTE(MID(Data1!G3,FIND("H",Data1!G3)+1,FIND("L",Data1!G3)-FIND("H",Data1!G3)-1),"Ø","0")) -> 87 | I6: =VALUE(SUBSTITUTE(MID(Data1!H3,FIND("H",Data1!H3)+1,FIND("L",Data1!H3)-FIND("H",Data1!H3)-1),"Ø","0")) -> 92 | J6: =VALUE(SUBSTITUTE(MID(Data1!I3,FIND("H",Data1!I3)+1,FIND("L",Data1!I3)-FIND("H",Data1!I3)-1),"Ø","0")) -> 96 | K6: =VALUE(SUBSTITUTE(MID(Data1!J3,FIND("H",Data1!J3)+1,FIND("L",Data1!J3)-FIND("H",Data1!J3)-1),"Ø","0")) -> 97 | ... O6: =VALUE(SUBSTITUTE(MID(Data1!N3,FIND("H",Data1!N3)+1,FIND("L",Data1!N3)-FIND("H",Data1!N3)-1),"Ø","0")) -> 63 | Q6: =SUM(L5:O14) -> 2506
B7: Baltimore | C7: =VLOOKUP(B7,Data1!A4:B53,2,FALSE) -> Maryland | D7: =VALUE(SUBSTITUTE(MID(Data1!C4,FIND("H",Data1!C4)+1,FIND("L",Data1!C4)-FIND("H",Data1!C4)-1),"Ø","0")) -> 41 | E7: =VALUE(SUBSTITUTE(MID(Data1!D4,FIND("H",Data1!D4)+1,FIND("L",Data1!D4)-FIND("H",Data1!D4)-1),"Ø","0")) -> 45 | F7: =VALUE(SUBSTITUTE(MID(Data1!E4,FIND("H",Data1!E4)+1,FIND("L",Data1!E4)-FIND("H",Data1!E4)-1),"Ø","0")) -> 54 | G7: =VALUE(SUBSTITUTE(MID(Data1!F4,FIND("H",Data1!F4)+1,FIND("L",Data1!F4)-FIND("H",Data1!F4)-1),"Ø","0")) -> 65 | H7: =VALUE(SUBSTITUTE(MID(Data1!G4,FIND("H",Data1!G4)+1,FIND("L",Data1!G4)-FIND("H",Data1!G4)-1),"Ø","0")) -> 74 | I7: =VALUE(SUBSTITUTE(MID(Data1!H4,FIND("H",Data1!H4)+1,FIND("L",Data1!H4)-FIND("H",Data1!H4)-1),"Ø","0")) -> 83 | J7: =VALUE(SUBSTITUTE(MID(Data1!I4,FIND("H",Data1!I4)+1,FIND("L",Data1!I4)-FIND("H",Data1!I4)-1),"Ø","0")) -> 87 | K7: =VALUE(SUBSTITUTE(MID(Data1!J4,FIND("H",Data1!J4)+1,FIND("L",Data1!J4)-FIND("H",Data1!J4)-1),"Ø","0")) -> 85 | ... O7: =VALUE(SUBSTITUTE(MID(Data1!N4,FIND("H",Data1!N4)+1,FIND("L",Data1!N4)-FIND("H",Data1!N4)-1),"Ø","0")) -> 45 | V7: {=INDEX(SummaryHigh!D4:O54,,MATCH(Q2,D4:O4,0))} -> Jan
B8: Birmingham | C8: =VLOOKUP(B8,Data1!A5:B54,2,FALSE) -> Alabama | D8: =VALUE(SUBSTITUTE(MID(Data1!C5,FIND("H",Data1!C5)+1,FIND("L",Data1!C5)-FIND("H",Data1!C5)-1),"Ø","0")) -> 54 | E8: =VALUE(SUBSTITUTE(MID(Data1!D5,FIND("H",Data1!D5)+1,FIND("L",Data1!D5)-FIND("H",Data1!D5)-1),"Ø","0")) -> 58 | F8: =VALUE(SUBSTITUTE(MID(Data1!E5,FIND("H",Data1!E5)+1,FIND("L",Data1!E5)-FIND("H",Data1!E5)-1),"Ø","0")) -> 67 | G8: =VALUE(SUBSTITUTE(MID(Data1!F5,FIND("H",Data1!F5)+1,FIND("L",Data1!F5)-FIND("H",Data1!F5)-1),"Ø","0")) -> 74 | H8: =VALUE(SUBSTITUTE(MID(Data1!G5,FIND("H",Data1!G5)+1,FIND("L",Data1!G5)-FIND("H",Data1!G5)-1),"Ø","0")) -> 82 | I8: =VALUE(SUBSTITUTE(MID(Data1!H5,FIND("H",Data1!H5)+1,FIND("L",Data1!H5)-FIND("H",Data1!H5)-1),"Ø","0")) -> 88 | J8: =VALUE(SUBSTITUTE(MID(Data1!I5,FIND("H",Data1!I5)+1,FIND("L",Data1!I5)-FIND("H",Data1!I5)-1),"Ø","0")) -> 91 | K8: =VALUE(SUBSTITUTE(MID(Data1!J5,FIND("H",Data1!J5)+1,FIND("L",Data1!J5)-FIND("H",Data1!J5)-1),"Ø","0")) -> 91 | ... O8: =VALUE(SUBSTITUTE(MID(Data1!N5,FIND("H",Data1!N5)+1,FIND("L",Data1!N5)-FIND("H",Data1!N5)-1),"Ø","0")) -> 56 | V8: 52 | W8: {=CHOOSE({1,2}, B5:B54, INDEX(D5:O54,,MATCH(Q2,D4:O4,0)))} -> Atlanta | X8: 52 | Y8: {=_xlfn.SORTBY(CHOOSE({1,2}, SummaryHigh!B5:B54, INDEX(SummaryHigh!D5:O54,,MATCH(Q2, SummaryHigh!D4:O4,0))), INDEX(SummaryHigh!D5:O54,,MATCH(Q2, SummaryHigh!D4:O4,0)), 1, SummaryHigh!B5:B54, 1)} -> Minneapolis | Z8: 24
B9: Boston | C9: =VLOOKUP(B9,Data1!A6:B55,2,FALSE) -> Massachusetts | D9: =VALUE(SUBSTITUTE(MID(Data1!C6,FIND("H",Data1!C6)+1,FIND("L",Data1!C6)-FIND("H",Data1!C6)-1),"Ø","0")) -> 36 | E9: =VALUE(SUBSTITUTE(MID(Data1!D6,FIND("H",Data1!D6)+1,FIND("L",Data1!D6)-FIND("H",Data1!D6)-1),"Ø","0")) -> 39 | F9: =VALUE(SUBSTITUTE(MID(Data1!E6,FIND("H",Data1!E6)+1,FIND("L",Data1!E6)-FIND("H",Data1!E6)-1),"Ø","0")) -> 45 | G9: =VALUE(SUBSTITUTE(MID(Data1!F6,FIND("H",Data1!F6)+1,FIND("L",Data1!F6)-FIND("H",Data1!F6)-1),"Ø","0")) -> 56 | H9: =VALUE(SUBSTITUTE(MID(Data1!G6,FIND("H",Data1!G6)+1,FIND("L",Data1!G6)-FIND("H",Data1!G6)-1),"Ø","0")) -> 66 | I9: =VALUE(SUBSTITUTE(MID(Data1!H6,FIND("H",Data1!H6)+1,FIND("L",Data1!H6)-FIND("H",Data1!H6)-1),"Ø","0")) -> 76 | J9: =VALUE(SUBSTITUTE(MID(Data1!I6,FIND("H",Data1!I6)+1,FIND("L",Data1!I6)-FIND("H",Data1!I6)-1),"Ø","0")) -> 81 | K9: =VALUE(SUBSTITUTE(MID(Data1!J6,FIND("H",Data1!J6)+1,FIND("L",Data1!J6)-FIND("H",Data1!J6)-1),"Ø","0")) -> 80 | ... O9: =VALUE(SUBSTITUTE(MID(Data1!N6,FIND("H",Data1!N6)+1,FIND("L",Data1!N6)-FIND("H",Data1!N6)-1),"Ø","0")) -> 41 | V9: 62 | W9: Austin | X9: 62 | Y9: Milwaukee | Z9: 29
B10: Buffalo | C10: =VLOOKUP(B10,Data1!A7:B56,2,FALSE) -> New York | D10: =VALUE(SUBSTITUTE(MID(Data1!C7,FIND("H",Data1!C7)+1,FIND("L",Data1!C7)-FIND("H",Data1!C7)-1),"Ø","0")) -> 31 | E10: =VALUE(SUBSTITUTE(MID(Data1!D7,FIND("H",Data1!D7)+1,FIND("L",Data1!D7)-FIND("H",Data1!D7)-1),"Ø","0")) -> 33 | F10: =VALUE(SUBSTITUTE(MID(Data1!E7,FIND("H",Data1!E7)+1,FIND("L",Data1!E7)-FIND("H",Data1!E7)-1),"Ø","0")) -> 42 | G10: =VALUE(SUBSTITUTE(MID(Data1!F7,FIND("H",Data1!F7)+1,FIND("L",Data1!F7)-FIND("H",Data1!F7)-1),"Ø","0")) -> 55 | H10: =VALUE(SUBSTITUTE(MID(Data1!G7,FIND("H",Data1!G7)+1,FIND("L",Data1!G7)-FIND("H",Data1!G7)-1),"Ø","0")) -> 67 | I10: =VALUE(SUBSTITUTE(MID(Data1!H7,FIND("H",Data1!H7)+1,FIND("L",Data1!H7)-FIND("H",Data1!H7)-1),"Ø","0")) -> 75 | J10: =VALUE(SUBSTITUTE(MID(Data1!I7,FIND("H",Data1!I7)+1,FIND("L",Data1!I7)-FIND("H",Data1!I7)-1),"Ø","0")) -> 80 | K10: =VALUE(SUBSTITUTE(MID(Data1!J7,FIND("H",Data1!J7)+1,FIND("L",Data1!J7)-FIND("H",Data1!J7)-1),"Ø","0")) -> 78 | ... O10: =VALUE(SUBSTITUTE(MID(Data1!N7,FIND("H",Data1!N7)+1,FIND("L",Data1!N7)-FIND("H",Data1!N7)-1),"Ø","0")) -> 36 | R10: {=CHOOSE({1,2},SummaryHigh!B5:B54,INDEX(SummaryHigh!D5:O54,,MATCH(Q2,SummaryHigh!D4:O4,0)))} -> Atlanta | S10: 52 | V10: 41 | W10: Baltimore | X10: 41 | Y10: Buffalo | Z10: 31
B11: Charlotte | C11: =VLOOKUP(B11,Data1!A8:B57,2,FALSE) -> North Carolina | D11: =VALUE(SUBSTITUTE(MID(Data1!C8,FIND("H",Data1!C8)+1,FIND("L",Data1!C8)-FIND("H",Data1!C8)-1),"Ø","0")) -> 51 | E11: =VALUE(SUBSTITUTE(MID(Data1!D8,FIND("H",Data1!D8)+1,FIND("L",Data1!D8)-FIND("H",Data1!D8)-1),"Ø","0")) -> 55 | F11: =VALUE(SUBSTITUTE(MID(Data1!E8,FIND("H",Data1!E8)+1,FIND("L",Data1!E8)-FIND("H",Data1!E8)-1),"Ø","0")) -> 63 | G11: =VALUE(SUBSTITUTE(MID(Data1!F8,FIND("H",Data1!F8)+1,FIND("L",Data1!F8)-FIND("H",Data1!F8)-1),"Ø","0")) -> 72 | H11: =VALUE(SUBSTITUTE(MID(Data1!G8,FIND("H",Data1!G8)+1,FIND("L",Data1!G8)-FIND("H",Data1!G8)-1),"Ø","0")) -> 79 | I11: =VALUE(SUBSTITUTE(MID(Data1!H8,FIND("H",Data1!H8)+1,FIND("L",Data1!H8)-FIND("H",Data1!H8)-1),"Ø","0")) -> 86 | J11: =VALUE(SUBSTITUTE(MID(Data1!I8,FIND("H",Data1!I8)+1,FIND("L",Data1!I8)-FIND("H",Data1!I8)-1),"Ø","0")) -> 89 | K11: =VALUE(SUBSTITUTE(MID(Data1!J8,FIND("H",Data1!J8)+1,FIND("L",Data1!J8)-FIND("H",Data1!J8)-1),"Ø","0")) -> 88 | ... O11: =VALUE(SUBSTITUTE(MID(Data1!N8,FIND("H",Data1!N8)+1,FIND("L",Data1!N8)-FIND("H",Data1!N8)-1),"Ø","0")) -> 53 | R11: Austin | S11: 62 | V11: 54 | W11: Birmingham | X11: 54 | Y11: Chicago | Z11: 31
B12: Chicago | C12: =VLOOKUP(B12,Data1!A9:B58,2,FALSE) -> Illinois | D12: =VALUE(SUBSTITUTE(MID(Data1!C9,FIND("H",Data1!C9)+1,FIND("L",Data1!C9)-FIND("H",Data1!C9)-1),"Ø","0")) -> 31 | E12: =VALUE(SUBSTITUTE(MID(Data1!D9,FIND("H",Data1!D9)+1,FIND("L",Data1!D9)-FIND("H",Data1!D9)-1),"Ø","0")) -> 35 | F12: =VALUE(SUBSTITUTE(MID(Data1!E9,FIND("H",Data1!E9)+1,FIND("L",Data1!E9)-FIND("H",Data1!E9)-1),"Ø","0")) -> 47 | G12: =VALUE(SUBSTITUTE(MID(Data1!F9,FIND("H",Data1!F9)+1,FIND("L",Data1!F9)-FIND("H",Data1!F9)-1),"Ø","0")) -> 59 | H12: =VALUE(SUBSTITUTE(MID(Data1!G9,FIND("H",Data1!G9)+1,FIND("L",Data1!G9)-FIND("H",Data1!G9)-1),"Ø","0")) -> 70 | I12: =VALUE(SUBSTITUTE(MID(Data1!H9,FIND("H",Data1!H9)+1,FIND("L",Data1!H9)-FIND("H",Data1!H9)-1),"Ø","0")) -> 80 | J12: =VALUE(SUBSTITUTE(MID(Data1!I9,FIND("H",Data1!I9)+1,FIND("L",Data1!I9)-FIND("H",Data1!I9)-1),"Ø","0")) -> 84 | K12: =VALUE(SUBSTITUTE(MID(Data1!J9,FIND("H",Data1!J9)+1,FIND("L",Data1!J9)-FIND("H",Data1!J9)-1),"Ø","0")) -> 82 | ... O12: =VALUE(SUBSTITUTE(MID(Data1!N9,FIND("H",Data1!N9)+1,FIND("L",Data1!N9)-FIND("H",Data1!N9)-1),"Ø","0")) -> 35 | R12: Baltimore | S12: 41 | V12: 36 | W12: Boston | X12: 36 | Y12: Detroit | Z12: 32
B13: Cincinnati | C13: =VLOOKUP(B13,Data1!A10:B59,2,FALSE) -> Ohio | D13: =VALUE(SUBSTITUTE(MID(Data1!C10,FIND("H",Data1!C10)+1,FIND("L",Data1!C10)-FIND("H",Data1!C10)-1),"Ø","0")) -> 40 | E13: =VALUE(SUBSTITUTE(MID(Data1!D10,FIND("H",Data1!D10)+1,FIND("L",Data1!D10)-FIND("H",Data1!D10)-1),"Ø","0")) -> 45 | F13: =VALUE(SUBSTITUTE(MID(Data1!E10,FIND("H",Data1!E10)+1,FIND("L",Data1!E10)-FIND("H",Data1!E10)-1),"Ø","0")) -> 55 | G13: =VALUE(SUBSTITUTE(MID(Data1!F10,FIND("H",Data1!F10)+1,FIND("L",Data1!F10)-FIND("H",Data1!F10)-1),"Ø","0")) -> 66 | H13: =VALUE(SUBSTITUTE(MID(Data1!G10,FIND("H",Data1!G10)+1,FIND("L",Data1!G10)-FIND("H",Data1!G10)-1),"Ø","0")) -> 75 | I13: =VALUE(SUBSTITUTE(MID(Data1!H10,FIND("H",Data1!H10)+1,FIND("L",Data1!H10)-FIND("H",Data1!H10)-1),"Ø","0")) -> 83 | J13: =VALUE(SUBSTITUTE(MID(Data1!I10,FIND("H",Data1!I10)+1,FIND("L",Data1!I10)-FIND("H",Data1!I10)-1),"Ø","0")) -> 87 | K13: =VALUE(SUBSTITUTE(MID(Data1!J10,FIND("H",Data1!J10)+1,FIND("L",Data1!J10)-FIND("H",Data1!J10)-1),"Ø","0")) -> 86 | ... O13: =VALUE(SUBSTITUTE(MID(Data1!N10,FIND("H",Data1!N10)+1,FIND("L",Data1!N10)-FIND("H",Data1!N10)-1),"Ø","0")) -> 43 | R13: Birmingham | S13: 54 | V13: 31 | W13: Buffalo | X13: 31 | Y13: Rochester | Z13: 32
B14: Cleveland | C14: =VLOOKUP(B14,Data1!A11:B60,2,FALSE) -> Ohio | D14: =VALUE(SUBSTITUTE(MID(Data1!C11,FIND("H",Data1!C11)+1,FIND("L",Data1!C11)-FIND("H",Data1!C11)-1),"Ø","0")) -> 34 | E14: =VALUE(SUBSTITUTE(MID(Data1!D11,FIND("H",Data1!D11)+1,FIND("L",Data1!D11)-FIND("H",Data1!D11)-1),"Ø","0")) -> 38 | F14: =VALUE(SUBSTITUTE(MID(Data1!E11,FIND("H",Data1!E11)+1,FIND("L",Data1!E11)-FIND("H",Data1!E11)-1),"Ø","0")) -> 47 | G14: =VALUE(SUBSTITUTE(MID(Data1!F11,FIND("H",Data1!F11)+1,FIND("L",Data1!F11)-FIND("H",Data1!F11)-1),"Ø","0")) -> 59 | H14: =VALUE(SUBSTITUTE(MID(Data1!G11,FIND("H",Data1!G11)+1,FIND("L",Data1!G11)-FIND("H",Data1!G11)-1),"Ø","0")) -> 70 | I14: =VALUE(SUBSTITUTE(MID(Data1!H11,FIND("H",Data1!H11)+1,FIND("L",Data1!H11)-FIND("H",Data1!H11)-1),"Ø","0")) -> 79 | J14: =VALUE(SUBSTITUTE(MID(Data1!I11,FIND("H",Data1!I11)+1,FIND("L",Data1!I11)-FIND("H",Data1!I11)-1),"Ø","0")) -> 83 | K14: =VALUE(SUBSTITUTE(MID(Data1!J11,FIND("H",Data1!J11)+1,FIND("L",Data1!J11)-FIND("H",Data1!J11)-1),"Ø","0")) -> 81 | ... O14: =VALUE(SUBSTITUTE(MID(Data1!N11,FIND("H",Data1!N11)+1,FIND("L",Data1!N11)-FIND("H",Data1!N11)-1),"Ø","0")) -> 38 | R14: Boston | S14: 36 | V14: 51 | W14: Charlotte | X14: 51 | Y14: Cleveland | Z14: 34
B15: Columbus | C15: =VLOOKUP(B15,Data1!A12:B61,2,FALSE) -> Ohio | D15: =VALUE(SUBSTITUTE(MID(Data1!C12,FIND("H",Data1!C12)+1,FIND("L",Data1!C12)-FIND("H",Data1!C12)-1),"Ø","0")) -> 37 | E15: =VALUE(SUBSTITUTE(MID(Data1!D12,FIND("H",Data1!D12)+1,FIND("L",Data1!D12)-FIND("H",Data1!D12)-1),"Ø","0")) -> 41 | F15: =VALUE(SUBSTITUTE(MID(Data1!E12,FIND("H",Data1!E12)+1,FIND("L",Data1!E12)-FIND("H",Data1!E12)-1),"Ø","0")) -> 51 | G15: =VALUE(SUBSTITUTE(MID(Data1!F12,FIND("H",Data1!F12)+1,FIND("L",Data1!F12)-FIND("H",Data1!F12)-1),"Ø","0")) -> 64 | H15: =VALUE(SUBSTITUTE(MID(Data1!G12,FIND("H",Data1!G12)+1,FIND("L",Data1!G12)-FIND("H",Data1!G12)-1),"Ø","0")) -> 73 | I15: =VALUE(SUBSTITUTE(MID(Data1!H12,FIND("H",Data1!H12)+1,FIND("L",Data1!H12)-FIND("H",Data1!H12)-1),"Ø","0")) -> 82 | J15: =VALUE(SUBSTITUTE(MID(Data1!I12,FIND("H",Data1!I12)+1,FIND("L",Data1!I12)-FIND("H",Data1!I12)-1),"Ø","0")) -> 85 | K15: =VALUE(SUBSTITUTE(MID(Data1!J12,FIND("H",Data1!J12)+1,FIND("L",Data1!J12)-FIND("H",Data1!J12)-1),"Ø","0")) -> 84 | ... O15: =VALUE(SUBSTITUTE(MID(Data1!N12,FIND("H",Data1!N12)+1,FIND("L",Data1!N12)-FIND("H",Data1!N12)-1),"Ø","0")) -> 40 | R15: Buffalo | S15: 31 | V15: 31 | W15: Chicago | X15: 31 | Y15: Hartford | Z15: 35
B16: Dallas | C16: =VLOOKUP(B16,Data1!A13:B62,2,FALSE) -> Texas | D16: =VALUE(SUBSTITUTE(MID(Data1!C13,FIND("H",Data1!C13)+1,FIND("L",Data1!C13)-FIND("H",Data1!C13)-1),"Ø","0")) -> 57 | E16: =VALUE(SUBSTITUTE(MID(Data1!D13,FIND("H",Data1!D13)+1,FIND("L",Data1!D13)-FIND("H",Data1!D13)-1),"Ø","0")) -> 61 | F16: =VALUE(SUBSTITUTE(MID(Data1!E13,FIND("H",Data1!E13)+1,FIND("L",Data1!E13)-FIND("H",Data1!E13)-1),"Ø","0")) -> 69 | G16: =VALUE(SUBSTITUTE(MID(Data1!F13,FIND("H",Data1!F13)+1,FIND("L",Data1!F13)-FIND("H",Data1!F13)-1),"Ø","0")) -> 77 | H16: =VALUE(SUBSTITUTE(MID(Data1!G13,FIND("H",Data1!G13)+1,FIND("L",Data1!G13)-FIND("H",Data1!G13)-1),"Ø","0")) -> 84 | I16: =VALUE(SUBSTITUTE(MID(Data1!H13,FIND("H",Data1!H13)+1,FIND("L",Data1!H13)-FIND("H",Data1!H13)-1),"Ø","0")) -> 92 | J16: =VALUE(SUBSTITUTE(MID(Data1!I13,FIND("H",Data1!I13)+1,FIND("L",Data1!I13)-FIND("H",Data1!I13)-1),"Ø","0")) -> 96 | K16: =VALUE(SUBSTITUTE(MID(Data1!J13,FIND("H",Data1!J13)+1,FIND("L",Data1!J13)-FIND("H",Data1!J13)-1),"Ø","0")) -> 96 | ... O16: =VALUE(SUBSTITUTE(MID(Data1!N13,FIND("H",Data1!N13)+1,FIND("L",Data1!N13)-FIND("H",Data1!N13)-1),"Ø","0")) -> 58 | R16: Charlotte | S16: 51 | V16: 40 | W16: Cincinnati | X16: 40 | Y16: Boston | Z16: 36
B17: Denver | C17: =VLOOKUP(B17,Data1!A14:B63,2,FALSE) -> Colorado | D17: =VALUE(SUBSTITUTE(MID(Data1!C14,FIND("H",Data1!C14)+1,FIND("L",Data1!C14)-FIND("H",Data1!C14)-1),"Ø","0")) -> 45 | E17: =VALUE(SUBSTITUTE(MID(Data1!D14,FIND("H",Data1!D14)+1,FIND("L",Data1!D14)-FIND("H",Data1!D14)-1),"Ø","0")) -> 46 | F17: =VALUE(SUBSTITUTE(MID(Data1!E14,FIND("H",Data1!E14)+1,FIND("L",Data1!E14)-FIND("H",Data1!E14)-1),"Ø","0")) -> 54 | G17: =VALUE(SUBSTITUTE(MID(Data1!F14,FIND("H",Data1!F14)+1,FIND("L",Data1!F14)-FIND("H",Data1!F14)-1),"Ø","0")) -> 61 | H17: =VALUE(SUBSTITUTE(MID(Data1!G14,FIND("H",Data1!G14)+1,FIND("L",Data1!G14)-FIND("H",Data1!G14)-1),"Ø","0")) -> 71 | I17: =VALUE(SUBSTITUTE(MID(Data1!H14,FIND("H",Data1!H14)+1,FIND("L",Data1!H14)-FIND("H",Data1!H14)-1),"Ø","0")) -> 81 | J17: =VALUE(SUBSTITUTE(MID(Data1!I14,FIND("H",Data1!I14)+1,FIND("L",Data1!I14)-FIND("H",Data1!I14)-1),"Ø","0")) -> 88 | K17: =VALUE(SUBSTITUTE(MID(Data1!J14,FIND("H",Data1!J14)+1,FIND("L",Data1!J14)-FIND("H",Data1!J14)-1),"Ø","0")) -> 86 | ... O17: =VALUE(SUBSTITUTE(MID(Data1!N14,FIND("H",Data1!N14)+1,FIND("L",Data1!N14)-FIND("H",Data1!N14)-1),"Ø","0")) -> 43 | R17: Chicago | S17: 31 | V17: 34 | W17: Cleveland | X17: 34 | Y17: Indianapolis | Z17: 36
B18: Detroit | C18: =VLOOKUP(B18,Data1!A15:B64,2,FALSE) -> Michigan | D18: =VALUE(SUBSTITUTE(MID(Data1!C15,FIND("H",Data1!C15)+1,FIND("L",Data1!C15)-FIND("H",Data1!C15)-1),"Ø","0")) -> 32 | E18: =VALUE(SUBSTITUTE(MID(Data1!D15,FIND("H",Data1!D15)+1,FIND("L",Data1!D15)-FIND("H",Data1!D15)-1),"Ø","0")) -> 35 | F18: =VALUE(SUBSTITUTE(MID(Data1!E15,FIND("H",Data1!E15)+1,FIND("L",Data1!E15)-FIND("H",Data1!E15)-1),"Ø","0")) -> 46 | G18: =VALUE(SUBSTITUTE(MID(Data1!F15,FIND("H",Data1!F15)+1,FIND("L",Data1!F15)-FIND("H",Data1!F15)-1),"Ø","0")) -> 59 | H18: =VALUE(SUBSTITUTE(MID(Data1!G15,FIND("H",Data1!G15)+1,FIND("L",Data1!G15)-FIND("H",Data1!G15)-1),"Ø","0")) -> 70 | I18: =VALUE(SUBSTITUTE(MID(Data1!H15,FIND("H",Data1!H15)+1,FIND("L",Data1!H15)-FIND("H",Data1!H15)-1),"Ø","0")) -> 79 | J18: =VALUE(SUBSTITUTE(MID(Data1!I15,FIND("H",Data1!I15)+1,FIND("L",Data1!I15)-FIND("H",Data1!I15)-1),"Ø","0")) -> 83 | K18: =VALUE(SUBSTITUTE(MID(Data1!J15,FIND("H",Data1!J15)+1,FIND("L",Data1!J15)-FIND("H",Data1!J15)-1),"Ø","0")) -> 81 | ... O18: =VALUE(SUBSTITUTE(MID(Data1!N15,FIND("H",Data1!N15)+1,FIND("L",Data1!N15)-FIND("H",Data1!N15)-1),"Ø","0")) -> 36 | R18: Cincinnati | S18: 40 | V18: 37 | W18: Columbus | X18: 37 | Y18: Pittsburgh | Z18: 36
B19: Hartford | C19: =VLOOKUP(B19,Data1!A16:B65,2,FALSE) -> Connecticut | D19: =VALUE(SUBSTITUTE(MID(Data1!C16,FIND("H",Data1!C16)+1,FIND("L",Data1!C16)-FIND("H",Data1!C16)-1),"Ø","0")) -> 35 | E19: =VALUE(SUBSTITUTE(MID(Data1!D16,FIND("H",Data1!D16)+1,FIND("L",Data1!D16)-FIND("H",Data1!D16)-1),"Ø","0")) -> 39 | F19: =VALUE(SUBSTITUTE(MID(Data1!E16,FIND("H",Data1!E16)+1,FIND("L",Data1!E16)-FIND("H",Data1!E16)-1),"Ø","0")) -> 48 | G19: =VALUE(SUBSTITUTE(MID(Data1!F16,FIND("H",Data1!F16)+1,FIND("L",Data1!F16)-FIND("H",Data1!F16)-1),"Ø","0")) -> 61 | H19: =VALUE(SUBSTITUTE(MID(Data1!G16,FIND("H",Data1!G16)+1,FIND("L",Data1!G16)-FIND("H",Data1!G16)-1),"Ø","0")) -> 71 | I19: =VALUE(SUBSTITUTE(MID(Data1!H16,FIND("H",Data1!H16)+1,FIND("L",Data1!H16)-FIND("H",Data1!H16)-1),"Ø","0")) -> 80 | J19: =VALUE(SUBSTITUTE(MID(Data1!I16,FIND("H",Data1!I16)+1,FIND("L",Data1!I16)-FIND("H",Data1!I16)-1),"Ø","0")) -> 85 | K19: =VALUE(SUBSTITUTE(MID(Data1!J16,FIND("H",Data1!J16)+1,FIND("L",Data1!J16)-FIND("H",Data1!J16)-1),"Ø","0")) -> 83 | ... O19: =VALUE(SUBSTITUTE(MID(Data1!N16,FIND("H",Data1!N16)+1,FIND("L",Data1!N16)-FIND("H",Data1!N16)-1),"Ø","0")) -> 40 | R19: Cleveland | S19: 34 | V19: 57 | W19: Dallas | X19: 57 | Y19: Columbus | Z19: 37
B20: Houston | C20: =VLOOKUP(B20,Data1!A17:B66,2,FALSE) -> Texas | D20: =VALUE(SUBSTITUTE(MID(Data1!C17,FIND("H",Data1!C17)+1,FIND("L",Data1!C17)-FIND("H",Data1!C17)-1),"Ø","0")) -> 63 | E20: =VALUE(SUBSTITUTE(MID(Data1!D17,FIND("H",Data1!D17)+1,FIND("L",Data1!D17)-FIND("H",Data1!D17)-1),"Ø","0")) -> 66 | F20: =VALUE(SUBSTITUTE(MID(Data1!E17,FIND("H",Data1!E17)+1,FIND("L",Data1!E17)-FIND("H",Data1!E17)-1),"Ø","0")) -> 73 | G20: =VALUE(SUBSTITUTE(MID(Data1!F17,FIND("H",Data1!F17)+1,FIND("L",Data1!F17)-FIND("H",Data1!F17)-1),"Ø","0")) -> 80 | H20: =VALUE(SUBSTITUTE(MID(Data1!G17,FIND("H",Data1!G17)+1,FIND("L",Data1!G17)-FIND("H",Data1!G17)-1),"Ø","0")) -> 86 | I20: =VALUE(SUBSTITUTE(MID(Data1!H17,FIND("H",Data1!H17)+1,FIND("L",Data1!H17)-FIND("H",Data1!H17)-1),"Ø","0")) -> 91 | J20: =VALUE(SUBSTITUTE(MID(Data1!I17,FIND("H",Data1!I17)+1,FIND("L",Data1!I17)-FIND("H",Data1!I17)-1),"Ø","0")) -> 94 | K20: =VALUE(SUBSTITUTE(MID(Data1!J17,FIND("H",Data1!J17)+1,FIND("L",Data1!J17)-FIND("H",Data1!J17)-1),"Ø","0")) -> 95 | ... O20: =VALUE(SUBSTITUTE(MID(Data1!N17,FIND("H",Data1!N17)+1,FIND("L",Data1!N17)-FIND("H",Data1!N17)-1),"Ø","0")) -> 64 | R20: Columbus | S20: 37 | V20: 45 | W20: Denver | X20: 45 | Y20: Providence | Z20: 37
B21: Indianapolis | C21: =VLOOKUP(B21,Data1!A18:B67,2,FALSE) -> Indiana | D21: =VALUE(SUBSTITUTE(MID(Data1!C18,FIND("H",Data1!C18)+1,FIND("L",Data1!C18)-FIND("H",Data1!C18)-1),"Ø","0")) -> 36 | E21: =VALUE(SUBSTITUTE(MID(Data1!D18,FIND("H",Data1!D18)+1,FIND("L",Data1!D18)-FIND("H",Data1!D18)-1),"Ø","0")) -> 40 | F21: =VALUE(SUBSTITUTE(MID(Data1!E18,FIND("H",Data1!E18)+1,FIND("L",Data1!E18)-FIND("H",Data1!E18)-1),"Ø","0")) -> 52 | G21: =VALUE(SUBSTITUTE(MID(Data1!F18,FIND("H",Data1!F18)+1,FIND("L",Data1!F18)-FIND("H",Data1!F18)-1),"Ø","0")) -> 63 | H21: =VALUE(SUBSTITUTE(MID(Data1!G18,FIND("H",Data1!G18)+1,FIND("L",Data1!G18)-FIND("H",Data1!G18)-1),"Ø","0")) -> 73 | I21: =VALUE(SUBSTITUTE(MID(Data1!H18,FIND("H",Data1!H18)+1,FIND("L",Data1!H18)-FIND("H",Data1!H18)-1),"Ø","0")) -> 82 | J21: =VALUE(SUBSTITUTE(MID(Data1!I18,FIND("H",Data1!I18)+1,FIND("L",Data1!I18)-FIND("H",Data1!I18)-1),"Ø","0")) -> 85 | K21: =VALUE(SUBSTITUTE(MID(Data1!J18,FIND("H",Data1!J18)+1,FIND("L",Data1!J18)-FIND("H",Data1!J18)-1),"Ø","0")) -> 84 | ... O21: =VALUE(SUBSTITUTE(MID(Data1!N18,FIND("H",Data1!N18)+1,FIND("L",Data1!N18)-FIND("H",Data1!N18)-1),"Ø","0")) -> 39 | R21: Dallas | S21: 57 | V21: 32 | W21: Detroit | X21: 32 | Y21: Salt Lake City | Z21: 37
B22: Jacksonville | C22: =VLOOKUP(B22,Data1!A19:B68,2,FALSE) -> Florida | D22: =VALUE(SUBSTITUTE(MID(Data1!C19,FIND("H",Data1!C19)+1,FIND("L",Data1!C19)-FIND("H",Data1!C19)-1),"Ø","0")) -> 65 | E22: =VALUE(SUBSTITUTE(MID(Data1!D19,FIND("H",Data1!D19)+1,FIND("L",Data1!D19)-FIND("H",Data1!D19)-1),"Ø","0")) -> 68 | F22: =VALUE(SUBSTITUTE(MID(Data1!E19,FIND("H",Data1!E19)+1,FIND("L",Data1!E19)-FIND("H",Data1!E19)-1),"Ø","0")) -> 74 | G22: =VALUE(SUBSTITUTE(MID(Data1!F19,FIND("H",Data1!F19)+1,FIND("L",Data1!F19)-FIND("H",Data1!F19)-1),"Ø","0")) -> 79 | H22: =VALUE(SUBSTITUTE(MID(Data1!G19,FIND("H",Data1!G19)+1,FIND("L",Data1!G19)-FIND("H",Data1!G19)-1),"Ø","0")) -> 86 | I22: =VALUE(SUBSTITUTE(MID(Data1!H19,FIND("H",Data1!H19)+1,FIND("L",Data1!H19)-FIND("H",Data1!H19)-1),"Ø","0")) -> 90 | J22: =VALUE(SUBSTITUTE(MID(Data1!I19,FIND("H",Data1!I19)+1,FIND("L",Data1!I19)-FIND("H",Data1!I19)-1),"Ø","0")) -> 92 | K22: =VALUE(SUBSTITUTE(MID(Data1!J19,FIND("H",Data1!J19)+1,FIND("L",Data1!J19)-FIND("H",Data1!J19)-1),"Ø","0")) -> 91 | ... O22: =VALUE(SUBSTITUTE(MID(Data1!N19,FIND("H",Data1!N19)+1,FIND("L",Data1!N19)-FIND("H",Data1!N19)-1),"Ø","0")) -> 67 | R22: Denver | S22: 45 | V22: 35 | W22: Hartford | X22: 35 | Y22: New York | Z22: 38
... B38: Pittsburgh | C38: =VLOOKUP(B38,Data1!A35:B84,2,FALSE) -> Pennsylvania | D38: =VALUE(SUBSTITUTE(MID(Data1!C35,FIND("H",Data1!C35)+1,FIND("L",Data1!C35)-FIND("H",Data1!C35)-1),"Ø","0")) -> 36 | E38: =VALUE(SUBSTITUTE(MID(Data1!D35,FIND("H",Data1!D35)+1,FIND("L",Data1!D35)-FIND("H",Data1!D35)-1),"Ø","0")) -> 39 | F38: =VALUE(SUBSTITUTE(MID(Data1!E35,FIND("H",Data1!E35)+1,FIND("L",Data1!E35)-FIND("H",Data1!E35)-1),"Ø","0")) -> 49 | G38: =VALUE(SUBSTITUTE(MID(Data1!F35,FIND("H",Data1!F35)+1,FIND("L",Data1!F35)-FIND("H",Data1!F35)-1),"Ø","0")) -> 62 | H38: =VALUE(SUBSTITUTE(MID(Data1!G35,FIND("H",Data1!G35)+1,FIND("L",Data1!G35)-FIND("H",Data1!G35)-1),"Ø","0")) -> 71 | I38: =VALUE(SUBSTITUTE(MID(Data1!H35,FIND("H",Data1!H35)+1,FIND("L",Data1!H35)-FIND("H",Data1!H35)-1),"Ø","0")) -> 79 | J38: =VALUE(SUBSTITUTE(MID(Data1!I35,FIND("H",Data1!I35)+1,FIND("L",Data1!I35)-FIND("H",Data1!I35)-1),"Ø","0")) -> 83 | K38: =VALUE(SUBSTITUTE(MID(Data1!J35,FIND("H",Data1!J35)+1,FIND("L",Data1!J35)-FIND("H",Data1!J35)-1),"Ø","0")) -> 81 | ... O38: =VALUE(SUBSTITUTE(MID(Data1!N35,FIND("H",Data1!N35)+1,FIND("L",Data1!N35)-FIND("H",Data1!N35)-1),"Ø","0")) -> 39 | R38: New York | S38: 38 | V38: 71 | W38: Orlando | X38: 71 | Y38: Raleigh | Z38: 51
B39: Portland | C39: =VLOOKUP(B39,Data1!A36:B85,2,FALSE) -> Oregon | D39: =VALUE(SUBSTITUTE(MID(Data1!C36,FIND("H",Data1!C36)+1,FIND("L",Data1!C36)-FIND("H",Data1!C36)-1),"Ø","0")) -> 47 | E39: =VALUE(SUBSTITUTE(MID(Data1!D36,FIND("H",Data1!D36)+1,FIND("L",Data1!D36)-FIND("H",Data1!D36)-1),"Ø","0")) -> 51 | F39: =VALUE(SUBSTITUTE(MID(Data1!E36,FIND("H",Data1!E36)+1,FIND("L",Data1!E36)-FIND("H",Data1!E36)-1),"Ø","0")) -> 57 | G39: =VALUE(SUBSTITUTE(MID(Data1!F36,FIND("H",Data1!F36)+1,FIND("L",Data1!F36)-FIND("H",Data1!F36)-1),"Ø","0")) -> 62 | H39: =VALUE(SUBSTITUTE(MID(Data1!G36,FIND("H",Data1!G36)+1,FIND("L",Data1!G36)-FIND("H",Data1!G36)-1),"Ø","0")) -> 69 | I39: =VALUE(SUBSTITUTE(MID(Data1!H36,FIND("H",Data1!H36)+1,FIND("L",Data1!H36)-FIND("H",Data1!H36)-1)," ","")) -> 73 | J39: =VALUE(SUBSTITUTE(MID(Data1!I36,FIND("H",Data1!I36)+1,FIND("L",Data1!I36)-FIND("H",Data1!I36)-1),"Ø","0")) -> 81 | K39: =VALUE(SUBSTITUTE(MID(Data1!J36,FIND("H",Data1!J36)+1,FIND("L",Data1!J36)-FIND("H",Data1!J36)-1),"Ø","0")) -> 81 | L39: =VALUE(SUBSTITUTE(MID(Data1!K36,FIND("H",Data1!K36)+1,FIND("L",Data1!K36)-FIND("H",Data1!K36)-1),"Ø","0")) -> 75 | M39: =VALUE(SUBSTITUTE(MID(Data1!L36,FIND("H",Data1!L36)+1,FIND("L",Data1!L36)-FIND("H",Data1!L36)-1),"Ø","0")) -> 64 | N39: =VALUE(SUBSTITUTE(MID(Data1!M36,FIND("H",Data1!M36)+1,FIND("L",Data1!M36)-FIND("H",Data1!M36)-1)," ","")) -> 52 | O39: =VALUE(SUBSTITUTE(MID(Data1!N36,FIND("H",Data1!N36)+1,FIND("L",Data1!N36)-FIND("H",Data1!N36)-1),"Ø","0")) -> 45 | R39: Oklahoma City | S39: 50 | V39: 40 | W39: Philadelphia | X39: 40 | Y39: Atlanta | Z39: 52
B40: Providence | C40: =VLOOKUP(B40,Data1!A37:B86,2,FALSE) -> Rhode Island | D40: =VALUE(SUBSTITUTE(MID(Data1!C37,FIND("H",Data1!C37)+1,FIND("L",Data1!C37)-FIND("H",Data1!C37)-1),"Ø","0")) -> 37 | E40: =VALUE(SUBSTITUTE(MID(Data1!D37,FIND("H",Data1!D37)+1,FIND("L",Data1!D37)-FIND("H",Data1!D37)-1),"Ø","0")) -> 40 | F40: =VALUE(SUBSTITUTE(MID(Data1!E37,FIND("H",Data1!E37)+1,FIND("L",Data1!E37)-FIND("H",Data1!E37)-1),"Ø","0")) -> 48 | G40: =VALUE(SUBSTITUTE(MID(Data1!F37,FIND("H",Data1!F37)+1,FIND("L",Data1!F37)-FIND("H",Data1!F37)-1),"Ø","0")) -> 59 | H40: =VALUE(SUBSTITUTE(MID(Data1!G37,FIND("H",Data1!G37)+1,FIND("L",Data1!G37)-FIND("H",Data1!G37)-1),"Ø","0")) -> 68 | I40: =VALUE(SUBSTITUTE(MID(Data1!H37,FIND("H",Data1!H37)+1,FIND("L",Data1!H37)-FIND("H",Data1!H37)-1),"Ø","0")) -> 78 | J40: =VALUE(SUBSTITUTE(MID(Data1!I37,FIND("H",Data1!I37)+1,FIND("L",Data1!I37)-FIND("H",Data1!I37)-1),"Ø","0")) -> 83 | K40: =VALUE(SUBSTITUTE(MID(Data1!J37,FIND("H",Data1!J37)+1,FIND("L",Data1!J37)-FIND("H",Data1!J37)-1),"Ø","0")) -> 81 | ... O40: =VALUE(SUBSTITUTE(MID(Data1!N37,FIND("H",Data1!N37)+1,FIND("L",Data1!N37)-FIND("H",Data1!N37)-1),"Ø","0")) -> 42 | R40: Orlando | S40: 71 | V40: 69 | W40: Phoenix | X40: 69 | Y40: Birmingham | Z40: 54
B41: Raleigh | C41: =VLOOKUP(B41,Data1!A38:B87,2,FALSE) -> North Carolina | D41: =VALUE(SUBSTITUTE(MID(Data1!C38,FIND("H",Data1!C38)+1,FIND("L",Data1!C38)-FIND("H",Data1!C38)-1),"Ø","0")) -> 51 | E41: =VALUE(SUBSTITUTE(MID(Data1!D38,FIND("H",Data1!D38)+1,FIND("L",Data1!D38)-FIND("H",Data1!D38)-1),"Ø","0")) -> 55 | F41: =VALUE(SUBSTITUTE(MID(Data1!E38,FIND("H",Data1!E38)+1,FIND("L",Data1!E38)-FIND("H",Data1!E38)-1),"Ø","0")) -> 63 | G41: =VALUE(SUBSTITUTE(MID(Data1!F38,FIND("H",Data1!F38)+1,FIND("L",Data1!F38)-FIND("H",Data1!F38)-1),"Ø","0")) -> 72 | H41: =VALUE(SUBSTITUTE(MID(Data1!G38,FIND("H",Data1!G38)+1,FIND("L",Data1!G38)-FIND("H",Data1!G38)-1),"Ø","0")) -> 80 | I41: =VALUE(SUBSTITUTE(MID(Data1!H38,FIND("H",Data1!H38)+1,FIND("L",Data1!H38)-FIND("H",Data1!H38)-1),"Ø","0")) -> 87 | J41: =VALUE(SUBSTITUTE(MID(Data1!I38,FIND("H",Data1!I38)+1,FIND("L",Data1!I38)-FIND("H",Data1!I38)-1),"Ø","0")) -> 90 | K41: =VALUE(SUBSTITUTE(MID(Data1!J38,FIND("H",Data1!J38)+1,FIND("L",Data1!J38)-FIND("H",Data1!J38)-1),"Ø","0")) -> 89 | ... O41: =VALUE(SUBSTITUTE(MID(Data1!N38,FIND("H",Data1!N38)+1,FIND("L",Data1!N38)-FIND("H",Data1!N38)-1),"Ø","0")) -> 54 | R41: Philadelphia | S41: 40 | V41: 36 | W41: Pittsburgh | X41: 36 | Y41: Sacramento | Z41: 54
B42: Richmond | C42: =VLOOKUP(B42,Data1!A39:B88,2,FALSE) -> Virginia | D42: =VALUE(SUBSTITUTE(MID(Data1!C39,FIND("H",Data1!C39)+1,FIND("L",Data1!C39)-FIND("H",Data1!C39)-1),"Ø","0")) -> 47 | E42: =VALUE(SUBSTITUTE(MID(Data1!D39,FIND("H",Data1!D39)+1,FIND("L",Data1!D39)-FIND("H",Data1!D39)-1),"Ø","0")) -> 51 | F42: =VALUE(SUBSTITUTE(MID(Data1!E39,FIND("H",Data1!E39)+1,FIND("L",Data1!E39)-FIND("H",Data1!E39)-1),"Ø","0")) -> 60 | G42: =VALUE(SUBSTITUTE(MID(Data1!F39,FIND("H",Data1!F39)+1,FIND("L",Data1!F39)-FIND("H",Data1!F39)-1),"Ø","0")) -> 70 | H42: =VALUE(SUBSTITUTE(MID(Data1!G39,FIND("H",Data1!G39)+1,FIND("L",Data1!G39)-FIND("H",Data1!G39)-1),"Ø","0")) -> 78 | I42: =VALUE(SUBSTITUTE(MID(Data1!H39,FIND("H",Data1!H39)+1,FIND("L",Data1!H39)-FIND("H",Data1!H39)-1),"Ø","0")) -> 86 | J42: =VALUE(SUBSTITUTE(MID(Data1!I39,FIND("H",Data1!I39)+1,FIND("L",Data1!I39)-FIND("H",Data1!I39)-1),"Ø","0")) -> 90 | K42: =VALUE(SUBSTITUTE(MID(Data1!J39,FIND("H",Data1!J39)+1,FIND("L",Data1!J39)-FIND("H",Data1!J39)-1),"Ø","0")) -> 88 | ... O42: =VALUE(SUBSTITUTE(MID(Data1!N39,FIND("H",Data1!N39)+1,FIND("L",Data1!N39)-FIND("H",Data1!N39)-1),"Ø","0")) -> 51 | R42: Phoenix | S42: 69 | V42: 47 | W42: Portland | X42: 47 | Y42: Dallas | Z42: 57
B43: Riverside | C43: =VLOOKUP(B43,Data1!A40:B89,2,FALSE) -> California | D43: =VALUE(SUBSTITUTE(MID(Data1!C40,FIND("H",Data1!C40)+1,FIND("L",Data1!C40)-FIND("H",Data1!C40)-1),"Ø","0")) -> 69 | E43: =VALUE(SUBSTITUTE(MID(Data1!D40,FIND("H",Data1!D40)+1,FIND("L",Data1!D40)-FIND("H",Data1!D40)-1),"Ø","0")) -> 70 | F43: =VALUE(SUBSTITUTE(MID(Data1!E40,FIND("H",Data1!E40)+1,FIND("L",Data1!E40)-FIND("H",Data1!E40)-1),"Ø","0")) -> 73 | G43: =VALUE(SUBSTITUTE(MID(Data1!F40,FIND("H",Data1!F40)+1,FIND("L",Data1!F40)-FIND("H",Data1!F40)-1),"Ø","0")) -> 78 | H43: =VALUE(SUBSTITUTE(MID(Data1!G40,FIND("H",Data1!G40)+1,FIND("L",Data1!G40)-FIND("H",Data1!G40)-1),"Ø","0")) -> 83 | I43: =VALUE(SUBSTITUTE(MID(Data1!H40,FIND("H",Data1!H40)+1,FIND("L",Data1!H40)-FIND("H",Data1!H40)-1),"Ø","0")) -> 89 | J43: =VALUE(SUBSTITUTE(MID(Data1!I40,FIND("H",Data1!I40)+1,FIND("L",Data1!I40)-FIND("H",Data1!I40)-1),"Ø","0")) -> 95 | K43: =VALUE(SUBSTITUTE(MID(Data1!J40,FIND("H",Data1!J40)+1,FIND("L",Data1!J40)-FIND("H",Data1!J40)-1),"Ø","0")) -> 96 | ... O43: =VALUE(SUBSTITUTE(MID(Data1!N40,FIND("H",Data1!N40)+1,FIND("L",Data1!N40)-FIND("H",Data1!N40)-1),"Ø","0")) -> 69 | R43: Pittsburgh | S43: 36 | V43: 37 | W43: Providence | X43: 37 | Y43: San Francisco | Z43: 57
B44: Rochester | C44: =VLOOKUP(B44,Data1!A41:B90,2,FALSE) -> New York | D44: =VALUE(SUBSTITUTE(MID(Data1!C41,FIND("H",Data1!C41)+1,FIND("L",Data1!C41)-FIND("H",Data1!C41)-1),"Ø","0")) -> 32 | E44: =VALUE(SUBSTITUTE(MID(Data1!D41,FIND("H",Data1!D41)+1,FIND("L",Data1!D41)-FIND("H",Data1!D41)-1),"Ø","0")) -> 34 | F44: =VALUE(SUBSTITUTE(MID(Data1!E41,FIND("H",Data1!E41)+1,FIND("L",Data1!E41)-FIND("H",Data1!E41)-1),"Ø","0")) -> 43 | G44: =VALUE(SUBSTITUTE(MID(Data1!F41,FIND("H",Data1!F41)+1,FIND("L",Data1!F41)-FIND("H",Data1!F41)-1),"Ø","0")) -> 56 | H44: =VALUE(SUBSTITUTE(MID(Data1!G41,FIND("H",Data1!G41)+1,FIND("L",Data1!G41)-FIND("H",Data1!G41)-1),"Ø","0")) -> 68 | I44: =VALUE(SUBSTITUTE(MID(Data1!H41,FIND("H",Data1!H41)+1,FIND("L",Data1!H41)-FIND("H",Data1!H41)-1),"Ø","0")) -> 77 | J44: =VALUE(SUBSTITUTE(MID(Data1!I41,FIND("H",Data1!I41)+1,FIND("L",Data1!I41)-FIND("H",Data1!I41)-1),"Ø","0")) -> 81 | K44: =VALUE(SUBSTITUTE(MID(Data1!J41,FIND("H",Data1!J41)+1,FIND("L",Data1!J41)-FIND("H",Data1!J41)-1),"Ø","0")) -> 79 | ... O44: =VALUE(SUBSTITUTE(MID(Data1!N41,FIND("H",Data1!N41)+1,FIND("L",Data1!N41)-FIND("H",Data1!N41)-1),"Ø","0")) -> 37 | R44: Portland | S44: 47 | V44: 51 | W44: Raleigh | X44: 51 | Y44: Las Vegas | Z44: 58
B45: Sacramento | C45: =VLOOKUP(B45,Data1!A42:B91,2,FALSE) -> California | D45: =VALUE(SUBSTITUTE(MID(Data1!C42,FIND("H",Data1!C42)+1,FIND("L",Data1!C42)-FIND("H",Data1!C42)-1),"Ø","0")) -> 54 | E45: =VALUE(SUBSTITUTE(MID(Data1!D42,FIND("H",Data1!D42)+1,FIND("L",Data1!D42)-FIND("H",Data1!D42)-1),"Ø","0")) -> 60 | F45: =VALUE(SUBSTITUTE(MID(Data1!E42,FIND("H",Data1!E42)+1,FIND("L",Data1!E42)-FIND("H",Data1!E42)-1),"Ø","0")) -> 65 | G45: =VALUE(SUBSTITUTE(MID(Data1!F42,FIND("H",Data1!F42)+1,FIND("L",Data1!F42)-FIND("H",Data1!F42)-1),"Ø","0")) -> 71 | H45: =VALUE(SUBSTITUTE(MID(Data1!G42,FIND("H",Data1!G42)+1,FIND("L",Data1!G42)-FIND("H",Data1!G42)-1),"Ø","0")) -> 80 | I45: =VALUE(SUBSTITUTE(MID(Data1!H42,FIND("H",Data1!H42)+1,FIND("L",Data1!H42)-FIND("H",Data1!H42)-1),"Ø","0")) -> 87 | J45: =VALUE(SUBSTITUTE(MID(Data1!I42,FIND("H",Data1!I42)+1,FIND("L",Data1!I42)-FIND("H",Data1!I42)-1),"Ø","0")) -> 92 | K45: =VALUE(SUBSTITUTE(MID(Data1!J42,FIND("H",Data1!J42)+1,FIND("L",Data1!J42)-FIND("H",Data1!J42)-1),"Ø","0")) -> 91 | ... O45: =VALUE(SUBSTITUTE(MID(Data1!N42,FIND("H",Data1!N42)+1,FIND("L",Data1!N42)-FIND("H",Data1!N42)-1),"Ø","0")) -> 54 | R45: Providence | S45: 37 | V45: 47 | W45: Richmond | X45: 47 | Y45: San Jose | Z45: 58
B46: Salt Lake City | C46: =VLOOKUP(B46,Data1!A43:B92,2,FALSE) -> Utah | D46: =VALUE(SUBSTITUTE(MID(Data1!C43,FIND("H",Data1!C43)+1,FIND("L",Data1!C43)-FIND("H",Data1!C43)-1),"Ø","0")) -> 37 | E46: =VALUE(SUBSTITUTE(MID(Data1!D43,FIND("H",Data1!D43)+1,FIND("L",Data1!D43)-FIND("H",Data1!D43)-1),"Ø","0")) -> 43 | F46: =VALUE(SUBSTITUTE(MID(Data1!E43,FIND("H",Data1!E43)+1,FIND("L",Data1!E43)-FIND("H",Data1!E43)-1),"Ø","0")) -> 54 | G46: =VALUE(SUBSTITUTE(MID(Data1!F43,FIND("H",Data1!F43)+1,FIND("L",Data1!F43)-FIND("H",Data1!F43)-1),"Ø","0")) -> 62 | H46: =VALUE(SUBSTITUTE(MID(Data1!G43,FIND("H",Data1!G43)+1,FIND("L",Data1!G43)-FIND("H",Data1!G43)-1),"Ø","0")) -> 72 | I46: =VALUE(SUBSTITUTE(MID(Data1!H43,FIND("H",Data1!H43)+1,FIND("L",Data1!H43)-FIND("H",Data1!H43)-1),"Ø","0")) -> 83 | J46: =VALUE(SUBSTITUTE(MID(Data1!I43,FIND("H",Data1!I43)+1,FIND("L",Data1!I43)-FIND("H",Data1!I43)-1),"Ø","0")) -> 93 | K46: =VALUE(SUBSTITUTE(MID(Data1!J43,FIND("H",Data1!J43)+1,FIND("L",Data1!J43)-FIND("H",Data1!J43)-1),"Ø","0")) -> 91 | ... O46: =VALUE(SUBSTITUTE(MID(Data1!N43,FIND("H",Data1!N43)+1,FIND("L",Data1!N43)-FIND("H",Data1!N43)-1),"Ø","0")) -> 38 | R46: Raleigh | S46: 51 | V46: 69 | W46: Riverside | X46: 69 | Y46: Austin | Z46: 62
B47: San Antonio | C47: =VLOOKUP(B47,Data1!A44:B93,2,FALSE) -> Texas | D47: =VALUE(SUBSTITUTE(MID(Data1!C44,FIND("H",Data1!C44)+1,FIND("L",Data1!C44)-FIND("H",Data1!C44)-1),"Ø","0")) -> 63 | E47: =VALUE(SUBSTITUTE(MID(Data1!D44,FIND("H",Data1!D44)+1,FIND("L",Data1!D44)-FIND("H",Data1!D44)-1),"Ø","0")) -> 67 | F47: =VALUE(SUBSTITUTE(MID(Data1!E44,FIND("H",Data1!E44)+1,FIND("L",Data1!E44)-FIND("H",Data1!E44)-1),"Ø","0")) -> 74 | G47: =VALUE(SUBSTITUTE(MID(Data1!F44,FIND("H",Data1!F44)+1,FIND("L",Data1!F44)-FIND("H",Data1!F44)-1),"Ø","0")) -> 81 | H47: =VALUE(SUBSTITUTE(MID(Data1!G44,FIND("H",Data1!G44)+1,FIND("L",Data1!G44)-FIND("H",Data1!G44)-1),"Ø","0")) -> 87 | I47: =VALUE(SUBSTITUTE(MID(Data1!H44,FIND("H",Data1!H44)+1,FIND("L",Data1!H44)-FIND("H",Data1!H44)-1),"Ø","0")) -> 92 | J47: =VALUE(SUBSTITUTE(MID(Data1!I44,FIND("H",Data1!I44)+1,FIND("L",Data1!I44)-FIND("H",Data1!I44)-1),"Ø","0")) -> 95 | K47: =VALUE(SUBSTITUTE(MID(Data1!J44,FIND("H",Data1!J44)+1,FIND("L",Data1!J44)-FIND("H",Data1!J44)-1),"Ø","0")) -> 96 | ... O47: =VALUE(SUBSTITUTE(MID(Data1!N44,FIND("H",Data1!N44)+1,FIND("L",Data1!N44)-FIND("H",Data1!N44)-1),"Ø","0")) -> 64 | R47: Richmond | S47: 47 | V47: 32 | W47: Rochester | X47: 32 | Y47: New Orleans | Z47: 62
B48: San Diego | C48: =VLOOKUP(B48,Data1!A45:B94,2,FALSE) -> California | D48: =VALUE(SUBSTITUTE(MID(Data1!C45,FIND("H",Data1!C45)+1,FIND("L",Data1!C45)-FIND("H",Data1!C45)-1),"Ø","0")) -> 65 | E48: =VALUE(SUBSTITUTE(MID(Data1!D45,FIND("H",Data1!D45)+1,FIND("L",Data1!D45)-FIND("H",Data1!D45)-1),"Ø","0")) -> 65 | F48: =VALUE(SUBSTITUTE(MID(Data1!E45,FIND("H",Data1!E45)+1,FIND("L",Data1!E45)-FIND("H",Data1!E45)-1),"Ø","0")) -> 66 | G48: =VALUE(SUBSTITUTE(MID(Data1!F45,FIND("H",Data1!F45)+1,FIND("L",Data1!F45)-FIND("H",Data1!F45)-1),"Ø","0")) -> 68 | H48: =VALUE(SUBSTITUTE(MID(Data1!G45,FIND("H",Data1!G45)+1,FIND("L",Data1!G45)-FIND("H",Data1!G45)-1),"Ø","0")) -> 69 | I48: =VALUE(SUBSTITUTE(MID(Data1!H45,FIND("H",Data1!H45)+1,FIND("L",Data1!H45)-FIND("H",Data1!H45)-1),"Ø","0")) -> 71 | J48: =VALUE(SUBSTITUTE(MID(Data1!I45,FIND("H",Data1!I45)+1,FIND("L",Data1!I45)-FIND("H",Data1!I45)-1),"Ø","0")) -> 75 | K48: =VALUE(SUBSTITUTE(MID(Data1!J45,FIND("H",Data1!J45)+1,FIND("L",Data1!J45)-FIND("H",Data1!J45)-1),"Ø","0")) -> 76 | ... O48: =VALUE(SUBSTITUTE(MID(Data1!N45,FIND("H",Data1!N45)+1,FIND("L",Data1!N45)-FIND("H",Data1!N45)-1),"Ø","0")) -> 65 | R48: Riverside | S48: 69 | V48: 54 | W48: Sacramento | X48: 54 | Y48: Houston | Z48: 63
B49: San Francisco | C49: =VLOOKUP(B49,Data1!A46:B95,2,FALSE) -> California | D49: =VALUE(SUBSTITUTE(MID(Data1!C46,FIND("H",Data1!C46)+1,FIND("L",Data1!C46)-FIND("H",Data1!C46)-1),"Ø","0")) -> 57 | E49: =VALUE(SUBSTITUTE(MID(Data1!D46,FIND("H",Data1!D46)+1,FIND("L",Data1!D46)-FIND("H",Data1!D46)-1),"Ø","0")) -> 60 | F49: =VALUE(SUBSTITUTE(MID(Data1!E46,FIND("H",Data1!E46)+1,FIND("L",Data1!E46)-FIND("H",Data1!E46)-1),"Ø","0")) -> 62 | G49: =VALUE(SUBSTITUTE(MID(Data1!F46,FIND("H",Data1!F46)+1,FIND("L",Data1!F46)-FIND("H",Data1!F46)-1),"Ø","0")) -> 63 | H49: =VALUE(SUBSTITUTE(MID(Data1!G46,FIND("H",Data1!G46)+1,FIND("L",Data1!G46)-FIND("H",Data1!G46)-1),"Ø","0")) -> 64 | I49: =VALUE(SUBSTITUTE(MID(Data1!H46,FIND("H",Data1!H46)+1,FIND("L",Data1!H46)-FIND("H",Data1!H46)-1),"Ø","0")) -> 66 | J49: =VALUE(SUBSTITUTE(MID(Data1!I46,FIND("H",Data1!I46)+1,FIND("L",Data1!I46)-FIND("H",Data1!I46)-1),"Ø","0")) -> 67 | K49: =VALUE(SUBSTITUTE(MID(Data1!J46,FIND("H",Data1!J46)+1,FIND("L",Data1!J46)-FIND("H",Data1!J46)-1),"Ø","0")) -> 68 | ... O49: =VALUE(SUBSTITUTE(MID(Data1!N46,FIND("H",Data1!N46)+1,FIND("L",Data1!N46)-FIND("H",Data1!N46)-1),"Ø","0")) -> 57 | R49: Rochester | S49: 32 | V49: 37 | W49: Salt Lake City | X49: 37 | Y49: San Antonio | Z49: 63
B50: San Jose | C50: =VLOOKUP(B50,Data1!A47:B96,2,FALSE) -> California | D50: =VALUE(SUBSTITUTE(MID(Data1!C47,FIND("H",Data1!C47)+1,FIND("L",Data1!C47)-FIND("H",Data1!C47)-1),"Ø","0")) -> 58 | E50: =VALUE(SUBSTITUTE(MID(Data1!D47,FIND("H",Data1!D47)+1,FIND("L",Data1!D47)-FIND("H",Data1!D47)-1),"Ø","0")) -> 62 | F50: =VALUE(SUBSTITUTE(MID(Data1!E47,FIND("H",Data1!E47)+1,FIND("L",Data1!E47)-FIND("H",Data1!E47)-1),"Ø","0")) -> 66 | G50: =VALUE(SUBSTITUTE(MID(Data1!F47,FIND("H",Data1!F47)+1,FIND("L",Data1!F47)-FIND("H",Data1!F47)-1),"Ø","0")) -> 69 | H50: =VALUE(SUBSTITUTE(MID(Data1!G47,FIND("H",Data1!G47)+1,FIND("L",Data1!G47)-FIND("H",Data1!G47)-1),"Ø","0")) -> 74 | I50: =VALUE(SUBSTITUTE(MID(Data1!H47,FIND("H",Data1!H47)+1,FIND("L",Data1!H47)-FIND("H",Data1!H47)-1),"Ø","0")) -> 79 | J50: =VALUE(SUBSTITUTE(MID(Data1!I47,FIND("H",Data1!I47)+1,FIND("L",Data1!I47)-FIND("H",Data1!I47)-1),"Ø","0")) -> 82 | K50: =VALUE(SUBSTITUTE(MID(Data1!J47,FIND("H",Data1!J47)+1,FIND("L",Data1!J47)-FIND("H",Data1!J47)-1),"Ø","0")) -> 82 | ... O50: =VALUE(SUBSTITUTE(MID(Data1!N47,FIND("H",Data1!N47)+1,FIND("L",Data1!N47)-FIND("H",Data1!N47)-1),"Ø","0")) -> 58 | R50: Sacramento | S50: 54 | V50: 63 | W50: San Antonio | X50: 63 | Y50: Jacksonville | Z50: 65
B51: Seattle | C51: =VLOOKUP(B51,Data1!A48:B97,2,FALSE) -> Washington | D51: =VALUE(SUBSTITUTE(MID(Data1!C48,FIND("H",Data1!C48)+1,FIND("L",Data1!C48)-FIND("H",Data1!C48)-1),"Ø","0")) -> 49 | E51: =VALUE(SUBSTITUTE(MID(Data1!D48,FIND("H",Data1!D48)+1,FIND("L",Data1!D48)-FIND("H",Data1!D48)-1),"Ø","0")) -> 51 | F51: =VALUE(SUBSTITUTE(MID(Data1!E48,FIND("H",Data1!E48)+1,FIND("L",Data1!E48)-FIND("H",Data1!E48)-1),"Ø","0")) -> 55 | G51: =VALUE(SUBSTITUTE(MID(Data1!F48,FIND("H",Data1!F48)+1,FIND("L",Data1!F48)-FIND("H",Data1!F48)-1),"Ø","0")) -> 60 | H51: =VALUE(SUBSTITUTE(MID(Data1!G48,FIND("H",Data1!G48)+1,FIND("L",Data1!G48)-FIND("H",Data1!G48)-1),"Ø","0")) -> 66 | I51: =VALUE(SUBSTITUTE(MID(Data1!H48,FIND("H",Data1!H48)+1,FIND("L",Data1!H48)-FIND("H",Data1!H48)-1),"Ø","0")) -> 71 | J51: =VALUE(SUBSTITUTE(MID(Data1!I48,FIND("H",Data1!I48)+1,FIND("L",Data1!I48)-FIND("H",Data1!I48)-1),"Ø","0")) -> 76 | K51: =VALUE(SUBSTITUTE(MID(Data1!J48,FIND("H",Data1!J48)+1,FIND("L",Data1!J48)-FIND("H",Data1!J48)-1),"Ø","0")) -> 76 | ... O51: =VALUE(SUBSTITUTE(MID(Data1!N48,FIND("H",Data1!N48)+1,FIND("L",Data1!N48)-FIND("H",Data1!N48)-1),"Ø","0")) -> 47 | R51: Salt Lake City | S51: 37 | V51: 65 | W51: San Diego | X51: 65 | Y51: San Diego | Z51: 65
... B54: Virginia Beach | C54: =VLOOKUP(B54,Data1!A51:B100,2,FALSE) -> Virginia | D54: =VALUE(SUBSTITUTE(MID(Data1!C51,FIND("H",Data1!C51)+1,FIND("L",Data1!C51)-FIND("H",Data1!C51)-1),"Ø","0")) -> 48 | E54: =VALUE(SUBSTITUTE(MID(Data1!D51,FIND("H",Data1!D51)+1,FIND("L",Data1!D51)-FIND("H",Data1!D51)-1),"Ø","0")) -> 51 | F54: =VALUE(SUBSTITUTE(MID(Data1!E51,FIND("H",Data1!E51)+1,FIND("L",Data1!E51)-FIND("H",Data1!E51)-1),"Ø","0")) -> 58 | G54: =VALUE(SUBSTITUTE(MID(Data1!F51,FIND("H",Data1!F51)+1,FIND("L",Data1!F51)-FIND("H",Data1!F51)-1),"Ø","0")) -> 68 | H54: =VALUE(SUBSTITUTE(MID(Data1!G51,FIND("H",Data1!G51)+1,FIND("L",Data1!G51)-FIND("H",Data1!G51)-1),"Ø","0")) -> 75 | I54: =VALUE(SUBSTITUTE(MID(Data1!H51,FIND("H",Data1!H51)+1,FIND("L",Data1!H51)-FIND("H",Data1!H51)-1),"Ø","0")) -> 84 | J54: =VALUE(SUBSTITUTE(MID(Data1!I51,FIND("H",Data1!I51)+1,FIND("L",Data1!I51)-FIND("H",Data1!I51)-1),"Ø","0")) -> 87 | K54: =VALUE(SUBSTITUTE(MID(Data1!J51,FIND("H",Data1!J51)+1,FIND("L",Data1!J51)-FIND("H",Data1!J51)-1),"Ø","0")) -> 85 | ... O54: =VALUE(SUBSTITUTE(MID(Data1!N51,FIND("H",Data1!N51)+1,FIND("L",Data1!N51)-FIND("H",Data1!N51)-1),"Ø","0")) -> 52 | R54: San Francisco | S54: 57 | V54: 49 | W54: Seattle | X54: 49 | Y54: Riverside | Z54: 69
B55: Highest Temperatures | D55: =MAX(D5:D54) -> 76 | E55: =MAX(E5:E54) -> 78 | F55: =MAX(F5:F54) -> 80 | G55: =MAX(G5:G54) -> 86 | H55: =MAX(H5:H54) -> 95 | I55: =MAX(I5:I54) -> 104 | J55: =MAX(J5:J54) -> 106 | K55: =MAX(K5:K54) -> 104 | ... O55: =MAX(O5:O54) -> 78 | R55: San Jose | S55: 58 | V55: 40 | W55: St. Louis | X55: 40 | Y55: Tampa | Z55: 70
R56: Seattle | S56: 49 | V56: 70 | W56: Tampa | X56: 70 | Y56: Orlando | Z56: 71
B57: Check Sum | D57: {=CheckSumHigh} -> 259045 | E57: 277026 | F57: 312012 | G57: 352569 | H57: 390367 | I57: 425245 | J57: 445112 | K57: 441332 | L57: 413908 | M57: 366926 | N57: 314215 | O57: 268310 | R57: St. Louis | S57: 40 | V57: 48 | W57: Virginia Beach | X57: 48 | Y57: Miami | Z57: 76
R58: Tampa | S58: 70
R59: Virginia Beach | S59: 48

Sheet SummaryLow
B3: Summary Table of Low Temperatures - by Month
B4: City | C4: State | D4: {=ListsMonthShort} -> Jan | E4: Feb | F4: Mar | G4: Apr | H4: May | I4: Jun | J4: Jul | K4: Aug | L4: Sep | M4: Oct | N4: Nov | O4: Dec
B5: {=ListCity} -> Atlanta | C5: =VLOOKUP(B5,Data1!A2:B51,2,FALSE) -> Georgia | D5: =VALUE(SUBSTITUTE(SUBSTITUTE(RIGHT(Data1!C2,LEN(Data1!C2)-FIND("L",Data1!C2)),"Ø","0")," ","")) -> 34 | E5: =VALUE(SUBSTITUTE(SUBSTITUTE(RIGHT(Data1!D2,LEN(Data1!D2)-FIND("L",Data1!D2)),"Ø","0")," ","")) -> 38 | F5: =VALUE(SUBSTITUTE(SUBSTITUTE(RIGHT(Data1!E2,LEN(Data1!E2)-FIND("L",Data1!E2)),"Ø","0")," ","")) -> 44 | G5: =VALUE(SUBSTITUTE(SUBSTITUTE(RIGHT(Data1!F2,LEN(Data1!F2)-FIND("L",Data1!F2)),"Ø","0")," ","")) -> 52 | H5: =VALUE(SUBSTITUTE(SUBSTITUTE(RIGHT(Data1!G2,LEN(Data1!G2)-FIND("L",Data1!G2)),"Ø","0")," ","")) -> 60 | I5: =VALUE(SUBSTITUTE(SUBSTITUTE(RIGHT(Data1!H2,LEN(Data1!H2)-FIND("L",Data1!H2)),"Ø","0")," ","")) -> 68 | J5: =VALUE(SUBSTITUTE(SUBSTITUTE(RIGHT(Data1!I2,LEN(Data1!I2)-FIND("L",Data1!I2)),"Ø","0")," ","")) -> 71 | K5: =VALUE(SUBSTITUTE(SUBSTITUTE(RIGHT(Data1!J2,LEN(Data1!J2)-FIND("L",Data1!J2)),"Ø","0")," ","")) -> 71 | ... O5: =VALUE(SUBSTITUTE(SUBSTITUTE(RIGHT(Data1!N2,LEN(Data1!N2)-FIND("L",Data1!N2)),"Ø","0")," ","")) -> 37
B6: Austin | C6: =VLOOKUP(B6,Data1!A3:B52,2,FALSE) -> Texas | D6: =VALUE(SUBSTITUTE(SUBSTITUTE(RIGHT(Data1!C3,LEN(Data1!C3)-FIND("L",Data1!C3)),"Ø","0")," ","")) -> 42 | E6: =VALUE(SUBSTITUTE(SUBSTITUTE(RIGHT(Data1!D3,LEN(Data1!D3)-FIND("L",Data1!D3)),"Ø","0")," ","")) -> 45 | F6: =VALUE(SUBSTITUTE(SUBSTITUTE(RIGHT(Data1!E3,LEN(Data1!E3)-FIND("L",Data1!E3)),"Ø","0")," ","")) -> 51 | G6: =VALUE(SUBSTITUTE(SUBSTITUTE(RIGHT(Data1!F3,LEN(Data1!F3)-FIND("L",Data1!F3)),"Ø","0")," ","")) -> 59 | H6: =VALUE(SUBSTITUTE(SUBSTITUTE(RIGHT(Data1!G3,LEN(Data1!G3)-FIND("L",Data1!G3)),"Ø","0")," ","")) -> 67 | I6: =VALUE(SUBSTITUTE(SUBSTITUTE(RIGHT(Data1!H3,LEN(Data1!H3)-FIND("L",Data1!H3)),"Ø","0")," ","")) -> 72 | J6: =VALUE(SUBSTITUTE(SUBSTITUTE(RIGHT(Data1!I3,LEN(Data1!I3)-FIND("L",Data1!I3)),"Ø","0")," ","")) -> 74 | K6: =VALUE(SUBSTITUTE(SUBSTITUTE(RIGHT(Data1!J3,LEN(Data1!J3)-FIND("L",Data1!J3)),"Ø","0")," ","")) -> 75 | ... O6: =VALUE(SUBSTITUTE(SUBSTITUTE(RIGHT(Data1!N3,LEN(Data1!N3)-FIND("L",Data1!N3)),"Ø","0")," ","")) -> 42
B7: Baltimore | C7: =VLOOKUP(B7,Data1!A4:B53,2,FALSE) -> Maryland | D7: =VALUE(SUBSTITUTE(SUBSTITUTE(RIGHT(Data1!C4,LEN(Data1!C4)-FIND("L",Data1!C4)),"Ø","0")," ","")) -> 24 | E7: =VALUE(SUBSTITUTE(SUBSTITUTE(RIGHT(Data1!D4,LEN(Data1!D4)-FIND("L",Data1!D4)),"Ø","0")," ","")) -> 27 | F7: =VALUE(SUBSTITUTE(SUBSTITUTE(RIGHT(Data1!E4,LEN(Data1!E4)-FIND("L",Data1!E4)),"Ø","0")," ","")) -> 34 | G7: =VALUE(SUBSTITUTE(SUBSTITUTE(RIGHT(Data1!F4,LEN(Data1!F4)-FIND("L",Data1!F4)),"Ø","0")," ","")) -> 43 | H7: =VALUE(SUBSTITUTE(SUBSTITUTE(RIGHT(Data1!G4,LEN(Data1!G4)-FIND("L",Data1!G4)),"Ø","0")," ","")) -> 52 | I7: =VALUE(SUBSTITUTE(SUBSTITUTE(RIGHT(Data1!H4,LEN(Data1!H4)-FIND("L",Data1!H4)),"Ø","0")," ","")) -> 62 | J7: =VALUE(SUBSTITUTE(SUBSTITUTE(RIGHT(Data1!I4,LEN(Data1!I4)-FIND("L",Data1!I4)),"Ø","0")," ","")) -> 67 | K7: =VALUE(SUBSTITUTE(SUBSTITUTE(RIGHT(Data1!J4,LEN(Data1!J4)-FIND("L",Data1!J4)),"Ø","0")," ","")) -> 65 | ... O7: =VALUE(SUBSTITUTE(SUBSTITUTE(RIGHT(Data1!N4,LEN(Data1!N4)-FIND("L",Data1!N4)),"Ø","0")," ","")) -> 28
B8: Birmingham | C8: =VLOOKUP(B8,Data1!A5:B54,2,FALSE) -> Alabama | D8: =VALUE(SUBSTITUTE(SUBSTITUTE(RIGHT(Data1!C5,LEN(Data1!C5)-FIND("L",Data1!C5)),"Ø","0")," ","")) -> 34 | E8: =VALUE(SUBSTITUTE(SUBSTITUTE(RIGHT(Data1!D5,LEN(Data1!D5)-FIND("L",Data1!D5)),"Ø","0")," ","")) -> 37 | F8: =VALUE(SUBSTITUTE(SUBSTITUTE(RIGHT(Data1!E5,LEN(Data1!E5)-FIND("L",Data1!E5)),"Ø","0")," ","")) -> 44 | G8: =VALUE(SUBSTITUTE(SUBSTITUTE(RIGHT(Data1!F5,LEN(Data1!F5)-FIND("L",Data1!F5)),"Ø","0")," ","")) -> 51 | H8: =VALUE(SUBSTITUTE(SUBSTITUTE(RIGHT(Data1!G5,LEN(Data1!G5)-FIND("L",Data1!G5)),"Ø","0")," ","")) -> 60 | I8: =VALUE(SUBSTITUTE(SUBSTITUTE(RIGHT(Data1!H5,LEN(Data1!H5)-FIND("L",Data1!H5)),"Ø","0")," ","")) -> 68 | J8: =VALUE(SUBSTITUTE(SUBSTITUTE(RIGHT(Data1!I5,LEN(Data1!I5)-FIND("L",Data1!I5)),"Ø","0")," ","")) -> 71 | K8: =VALUE(SUBSTITUTE(SUBSTITUTE(RIGHT(Data1!J5,LEN(Data1!J5)-FIND("L",Data1!J5)),"Ø","0")," ","")) -> 71 | ... O8: =VALUE(SUBSTITUTE(SUBSTITUTE(RIGHT(Data1!N5,LEN(Data1!N5)-FIND("L",Data1!N5)),"Ø","0")," ","")) -> 36
B9: Boston | C9: =VLOOKUP(B9,Data1!A6:B55,2,FALSE) -> Massachusetts | D9: =VALUE(SUBSTITUTE(SUBSTITUTE(RIGHT(Data1!C6,LEN(Data1!C6)-FIND("L",Data1!C6)),"Ø","0")," ","")) -> 22 | E9: =VALUE(SUBSTITUTE(SUBSTITUTE(RIGHT(Data1!D6,LEN(Data1!D6)-FIND("L",Data1!D6)),"Ø","0")," ","")) -> 25 | F9: =VALUE(SUBSTITUTE(SUBSTITUTE(RIGHT(Data1!E6,LEN(Data1!E6)-FIND("L",Data1!E6)),"Ø","0")," ","")) -> 31 | G9: =VALUE(SUBSTITUTE(SUBSTITUTE(RIGHT(Data1!F6,LEN(Data1!F6)-FIND("L",Data1!F6)),"Ø","0")," ","")) -> 41 | H9: =VALUE(SUBSTITUTE(SUBSTITUTE(RIGHT(Data1!G6,LEN(Data1!G6)-FIND("L",Data1!G6)),"Ø","0")," ","")) -> 50 | I9: =VALUE(SUBSTITUTE(SUBSTITUTE(RIGHT(Data1!H6,LEN(Data1!H6)-FIND("L",Data1!H6)),"Ø","0")," ","")) -> 60 | J9: =VALUE(SUBSTITUTE(SUBSTITUTE(RIGHT(Data1!I6,LEN(Data1!I6)-FIND("L",Data1!I6)),"Ø","0")," ","")) -> 65 | K9: =VALUE(SUBSTITUTE(SUBSTITUTE(RIGHT(Data1!J6,LEN(Data1!J6)-FIND("L",Data1!J6)),"Ø","0")," ","")) -> 65 | ... O9: =VALUE(SUBSTITUTE(SUBSTITUTE(RIGHT(Data1!N6,LEN(Data1!N6)-FIND("L",Data1!N6)),"Ø","0")," ","")) -> 28
B10: Buffalo | C10: =VLOOKUP(B10,Data1!A7:B56,2,FALSE) -> New York | D10: =VALUE(SUBSTITUTE(SUBSTITUTE(RIGHT(Data1!C7,LEN(Data1!C7)-FIND("L",Data1!C7)),"Ø","0")," ","")) -> 19 | E10: =VALUE(SUBSTITUTE(SUBSTITUTE(RIGHT(Data1!D7,LEN(Data1!D7)-FIND("L",Data1!D7)),"Ø","0")," ","")) -> 19 | F10: =VALUE(SUBSTITUTE(SUBSTITUTE(RIGHT(Data1!E7,LEN(Data1!E7)-FIND("L",Data1!E7)),"Ø","0")," ","")) -> 26 | G10: =VALUE(SUBSTITUTE(SUBSTITUTE(RIGHT(Data1!F7,LEN(Data1!F7)-FIND("L",Data1!F7)),"Ø","0")," ","")) -> 37 | H10: =VALUE(SUBSTITUTE(SUBSTITUTE(RIGHT(Data1!G7,LEN(Data1!G7)-FIND("L",Data1!G7)),"Ø","0")," ","")) -> 47 | I10: =VALUE(SUBSTITUTE(SUBSTITUTE(RIGHT(Data1!H7,LEN(Data1!H7)-FIND("L",Data1!H7)),"Ø","0")," ","")) -> 57 | J10: =VALUE(SUBSTITUTE(SUBSTITUTE(RIGHT(Data1!I7,LEN(Data1!I7)-FIND("L",Data1!I7)),"Ø","0")," ","")) -> 62 | K10: =VALUE(SUBSTITUTE(SUBSTITUTE(RIGHT(Data1!J7,LEN(Data1!J7)-FIND("L",Data1!J7)),"Ø","0")," ","")) -> 61 | ... O10: =VALUE(SUBSTITUTE(SUBSTITUTE(RIGHT(Data1!N7,LEN(Data1!N7)-FIND("L",Data1!N7)),"Ø","0")," ","")) -> 24
B11: Charlotte | C11: =VLOOKUP(B11,Data1!A8:B57,2,FALSE) -> North Carolina | D11: =VALUE(SUBSTITUTE(SUBSTITUTE(RIGHT(Data1!C8,LEN(Data1!C8)-FIND("L",Data1!C8)),"Ø","0")," ","")) -> 30 | E11: =VALUE(SUBSTITUTE(SUBSTITUTE(RIGHT(Data1!D8,LEN(Data1!D8)-FIND("L",Data1!D8)),"Ø","0")," ","")) -> 33 | F11: =VALUE(SUBSTITUTE(SUBSTITUTE(RIGHT(Data1!E8,LEN(Data1!E8)-FIND("L",Data1!E8)),"Ø","0")," ","")) -> 39 | G11: =VALUE(SUBSTITUTE(SUBSTITUTE(RIGHT(Data1!F8,LEN(Data1!F8)-FIND("L",Data1!F8)),"Ø","0")," ","")) -> 47 | H11: =VALUE(SUBSTITUTE(SUBSTITUTE(RIGHT(Data1!G8,LEN(Data1!G8)-FIND("L",Data1!G8)),"Ø","0")," ","")) -> 56 | I11: =VALUE(SUBSTITUTE(SUBSTITUTE(RIGHT(Data1!H8,LEN(Data1!H8)-FIND("L",Data1!H8)),"Ø","0")," ","")) -> 65 | J11: =VALUE(SUBSTITUTE(SUBSTITUTE(RIGHT(Data1!I8,LEN(Data1!I8)-FIND("L",Data1!I8)),"Ø","0")," ","")) -> 68 | K11: =VALUE(SUBSTITUTE(SUBSTITUTE(RIGHT(Data1!J8,LEN(Data1!J8)-FIND("L",Data1!J8)),"Ø","0")," ","")) -> 67 | ... O11: =VALUE(SUBSTITUTE(SUBSTITUTE(RIGHT(Data1!N8,LEN(Data1!N8)-FIND("L",Data1!N8)),"Ø","0")," ","")) -> 32
B12: Chicago | C12: =VLOOKUP(B12,Data1!A9:B58,2,FALSE) -> Illinois | D12: =VALUE(SUBSTITUTE(SUBSTITUTE(RIGHT(Data1!C9,LEN(Data1!C9)-FIND("L",Data1!C9)),"Ø","0")," ","")) -> 17 | E12: =VALUE(SUBSTITUTE(SUBSTITUTE(RIGHT(Data1!D9,LEN(Data1!D9)-FIND("L",Data1!D9)),"Ø","0")," ","")) -> 20 | F12: =VALUE(SUBSTITUTE(SUBSTITUTE(RIGHT(Data1!E9,LEN(Data1!E9)-FIND("L",Data1!E9)),"Ø","0")," ","")) -> 29 | G12: =VALUE(SUBSTITUTE(SUBSTITUTE(RIGHT(Data1!F9,LEN(Data1!F9)-FIND("L",Data1!F9)),"Ø","0")," ","")) -> 39 | H12: =VALUE(SUBSTITUTE(SUBSTITUTE(RIGHT(Data1!G9,LEN(Data1!G9)-FIND("L",Data1!G9)),"Ø","0")," ","")) -> 48 | I12: =VALUE(SUBSTITUTE(SUBSTITUTE(RIGHT(Data1!H9,LEN(Data1!H9)-FIND("L",Data1!H9)),"Ø","0")," ","")) -> 58 | J12: =VALUE(SUBSTITUTE(SUBSTITUTE(RIGHT(Data1!I9,LEN(Data1!I9)-FIND("L",Data1!I9)),"Ø","0")," ","")) -> 64 | K12: =VALUE(SUBSTITUTE(SUBSTITUTE(RIGHT(Data1!J9,LEN(Data1!J9)-FIND("L",Data1!J9)),"Ø","0")," ","")) -> 63 | ... O12: =VALUE(SUBSTITUTE(SUBSTITUTE(RIGHT(Data1!N9,LEN(Data1!N9)-FIND("L",Data1!N9)),"Ø","0")," ","")) -> 21
B13: Cincinnati | C13: =VLOOKUP(B13,Data1!A10:B59,2,FALSE) -> Ohio | D13: =VALUE(SUBSTITUTE(SUBSTITUTE(RIGHT(Data1!C10,LEN(Data1!C10)-FIND("L",Data1!C10)),"Ø","0")," ","")) -> 22 | E13: =VALUE(SUBSTITUTE(SUBSTITUTE(RIGHT(Data1!D10,LEN(Data1!D10)-FIND("L",Data1!D10)),"Ø","0")," ","")) -> 25 | F13: =VALUE(SUBSTITUTE(SUBSTITUTE(RIGHT(Data1!E10,LEN(Data1!E10)-FIND("L",Data1!E10)),"Ø","0")," ","")) -> 33 | G13: =VALUE(SUBSTITUTE(SUBSTITUTE(RIGHT(Data1!F10,LEN(Data1!F10)-FIND("L",Data1!F10)),"Ø","0")," ","")) -> 42 | H13: =VALUE(SUBSTITUTE(SUBSTITUTE(RIGHT(Data1!G10,LEN(Data1!G10)-FIND("L",Data1!G10)),"Ø","0")," ","")) -> 52 | I13: =VALUE(SUBSTITUTE(SUBSTITUTE(RIGHT(Data1!H10,LEN(Data1!H10)-FIND("L",Data1!H10)),"Ø","0")," ","")) -> 61 | J13: =VALUE(SUBSTITUTE(SUBSTITUTE(RIGHT(Data1!I10,LEN(Data1!I10)-FIND("L",Data1!I10)),"Ø","0")," ","")) -> 65 | K13: =VALUE(SUBSTITUTE(SUBSTITUTE(RIGHT(Data1!J10,LEN(Data1!J10)-FIND("L",Data1!J10)),"Ø","0")," ","")) -> 63 | ... O13: =VALUE(SUBSTITUTE(SUBSTITUTE(RIGHT(Data1!N10,LEN(Data1!N10)-FIND("L",Data1!N10)),"Ø","0")," ","")) -> 26
B14: Cleveland | C14: =VLOOKUP(B14,Data1!A11:B60,2,FALSE) -> Ohio | D14: =VALUE(SUBSTITUTE(SUBSTITUTE(RIGHT(Data1!C11,LEN(Data1!C11)-FIND("L",Data1!C11)),"Ø","0")," ","")) -> 22 | E14: =VALUE(SUBSTITUTE(SUBSTITUTE(RIGHT(Data1!D11,LEN(Data1!D11)-FIND("L",Data1!D11)),"Ø","0")," ","")) -> 24 | F14: =VALUE(SUBSTITUTE(SUBSTITUTE(RIGHT(Data1!E11,LEN(Data1!E11)-FIND("L",Data1!E11)),"Ø","0")," ","")) -> 30 | G14: =VALUE(SUBSTITUTE(SUBSTITUTE(RIGHT(Data1!F11,LEN(Data1!F11)-FIND("L",Data1!F11)),"Ø","0")," ","")) -> 40 | H14: =VALUE(SUBSTITUTE(SUBSTITUTE(RIGHT(Data1!G11,LEN(Data1!G11)-FIND("L",Data1!G11)),"Ø","0")," ","")) -> 50 | I14: =VALUE(SUBSTITUTE(SUBSTITUTE(RIGHT(Data1!H11,LEN(Data1!H11)-FIND("L",Data1!H11)),"Ø","0")," ","")) -> 60 | J14: =VALUE(SUBSTITUTE(SUBSTITUTE(RIGHT(Data1!I11,LEN(Data1!I11)-FIND("L",Data1!I11)),"Ø","0")," ","")) -> 64 | K14: =VALUE(SUBSTITUTE(SUBSTITUTE(RIGHT(Data1!J11,LEN(Data1!J11)-FIND("L",Data1!J11)),"Ø","0")," ","")) -> 63 | ... O14: =VALUE(SUBSTITUTE(SUBSTITUTE(RIGHT(Data1!N11,LEN(Data1!N11)-FIND("L",Data1!N11)),"Ø","0")," ","")) -> 26
B15: Columbus | C15: =VLOOKUP(B15,Data1!A12:B61,2,FALSE) -> Ohio | D15: =VALUE(SUBSTITUTE(SUBSTITUTE(RIGHT(Data1!C12,LEN(Data1!C12)-FIND("L",Data1!C12)),"Ø","0")," ","")) -> 23 | E15: =VALUE(SUBSTITUTE(SUBSTITUTE(RIGHT(Data1!D12,LEN(Data1!D12)-FIND("L",Data1!D12)),"Ø","0")," ","")) -> 25 | F15: =VALUE(SUBSTITUTE(SUBSTITUTE(RIGHT(Data1!E12,LEN(Data1!E12)-FIND("L",Data1!E12)),"Ø","0")," ","")) -> 33 | G15: =VALUE(SUBSTITUTE(SUBSTITUTE(RIGHT(Data1!F12,LEN(Data1!F12)-FIND("L",Data1!F12)),"Ø","0")," ","")) -> 43 | H15: =VALUE(SUBSTITUTE(SUBSTITUTE(RIGHT(Data1!G12,LEN(Data1!G12)-FIND("L",Data1!G12)),"Ø","0")," ","")) -> 52 | I15: =VALUE(SUBSTITUTE(SUBSTITUTE(RIGHT(Data1!H12,LEN(Data1!H12)-FIND("L",Data1!H12)),"Ø","0")," ","")) -> 62 | J15: =VALUE(SUBSTITUTE(SUBSTITUTE(RIGHT(Data1!I12,LEN(Data1!I12)-FIND("L",Data1!I12)),"Ø","0")," ","")) -> 66 | K15: =VALUE(SUBSTITUTE(SUBSTITUTE(RIGHT(Data1!J12,LEN(Data1!J12)-FIND("L",Data1!J12)),"Ø","0")," ","")) -> 64 | ... O15: =VALUE(SUBSTITUTE(SUBSTITUTE(RIGHT(Data1!N12,LEN(Data1!N12)-FIND("L",Data1!N12)),"Ø","0")," ","")) -> 27
B16: Dallas | C16: =VLOOKUP(B16,Data1!A13:B62,2,FALSE) -> Texas | D16: =VALUE(SUBSTITUTE(SUBSTITUTE(RIGHT(Data1!C13,LEN(Data1!C13)-FIND("L",Data1!C13)),"Ø","0")," ","")) -> 37 | E16: =VALUE(SUBSTITUTE(SUBSTITUTE(RIGHT(Data1!D13,LEN(Data1!D13)-FIND("L",Data1!D13)),"Ø","0")," ","")) -> 41 | F16: =VALUE(SUBSTITUTE(SUBSTITUTE(RIGHT(Data1!E13,LEN(Data1!E13)-FIND("L",Data1!E13)),"Ø","0")," ","")) -> 49 | G16: =VALUE(SUBSTITUTE(SUBSTITUTE(RIGHT(Data1!F13,LEN(Data1!F13)-FIND("L",Data1!F13)),"Ø","0")," ","")) -> 56 | H16: =VALUE(SUBSTITUTE(SUBSTITUTE(RIGHT(Data1!G13,LEN(Data1!G13)-FIND("L",Data1!G13)),"Ø","0")," ","")) -> 65 | I16: =VALUE(SUBSTITUTE(SUBSTITUTE(RIGHT(Data1!H13,LEN(Data1!H13)-FIND("L",Data1!H13)),"Ø","0")," ","")) -> 73 | J16: =VALUE(SUBSTITUTE(SUBSTITUTE(RIGHT(Data1!I13,LEN(Data1!I13)-FIND("L",Data1!I13)),"Ø","0")," ","")) -> 77 | K16: =VALUE(SUBSTITUTE(SUBSTITUTE(RIGHT(Data1!J13,LEN(Data1!J13)-FIND("L",Data1!J13)),"Ø","0")," ","")) -> 77 | ... O16: =VALUE(SUBSTITUTE(SUBSTITUTE(RIGHT(Data1!N13,LEN(Data1!N13)-FIND("L",Data1!N13)),"Ø","0")," ","")) -> 39
B17: Denver | C17: =VLOOKUP(B17,Data1!A14:B63,2,FALSE) -> Colorado | D17: =VALUE(SUBSTITUTE(SUBSTITUTE(RIGHT(Data1!C14,LEN(Data1!C14)-FIND("L",Data1!C14)),"Ø","0")," ","")) -> 17 | E17: =VALUE(SUBSTITUTE(SUBSTITUTE(RIGHT(Data1!D14,LEN(Data1!D14)-FIND("L",Data1!D14)),"Ø","0")," ","")) -> 20 | F17: =VALUE(SUBSTITUTE(SUBSTITUTE(RIGHT(Data1!E14,LEN(Data1!E14)-FIND("L",Data1!E14)),"Ø","0")," ","")) -> 26 | G17: =VALUE(SUBSTITUTE(SUBSTITUTE(RIGHT(Data1!F14,LEN(Data1!F14)-FIND("L",Data1!F14)),"Ø","0")," ","")) -> 34 | H17: =VALUE(SUBSTITUTE(SUBSTITUTE(RIGHT(Data1!G14,LEN(Data1!G14)-FIND("L",Data1!G14)),"Ø","0")," ","")) -> 44 | I17: =VALUE(SUBSTITUTE(SUBSTITUTE(RIGHT(Data1!H14,LEN(Data1!H14)-FIND("L",Data1!H14)),"Ø","0")," ","")) -> 53 | J17: =VALUE(SUBSTITUTE(SUBSTITUTE(RIGHT(Data1!I14,LEN(Data1!I14)-FIND("L",Data1!I14)),"Ø","0")," ","")) -> 59 | K17: =VALUE(SUBSTITUTE(SUBSTITUTE(RIGHT(Data1!J14,LEN(Data1!J14)-FIND("L",Data1!J14)),"Ø","0")," ","")) -> 57 | ... O17: =VALUE(SUBSTITUTE(SUBSTITUTE(RIGHT(Data1!N14,LEN(Data1!N14)-FIND("L",Data1!N14)),"Ø","0")," ","")) -> 17
... B54: Virginia Beach | C54: =VLOOKUP(B54,Data1!A51:B100,2,FALSE) -> Virginia | D54: =VALUE(SUBSTITUTE(SUBSTITUTE(RIGHT(Data1!C51,LEN(Data1!C51)-FIND("L",Data1!C51)),"Ø","0")," ","")) -> 33 | E54: =VALUE(SUBSTITUTE(SUBSTITUTE(RIGHT(Data1!D51,LEN(Data1!D51)-FIND("L",Data1!D51)),"Ø","0")," ","")) -> 34 | F54: =VALUE(SUBSTITUTE(SUBSTITUTE(RIGHT(Data1!E51,LEN(Data1!E51)-FIND("L",Data1!E51)),"Ø","0")," ","")) -> 41 | G54: =VALUE(SUBSTITUTE(SUBSTITUTE(RIGHT(Data1!F51,LEN(Data1!F51)-FIND("L",Data1!F51)),"Ø","0")," ","")) -> 49 | H54: =VALUE(SUBSTITUTE(SUBSTITUTE(RIGHT(Data1!G51,LEN(Data1!G51)-FIND("L",Data1!G51)),"Ø","0")," ","")) -> 58 | I54: =VALUE(SUBSTITUTE(SUBSTITUTE(RIGHT(Data1!H51,LEN(Data1!H51)-FIND("L",Data1!H51)),"Ø","0")," ","")) -> 67 | J54: =VALUE(SUBSTITUTE(SUBSTITUTE(RIGHT(Data1!I51,LEN(Data1!I51)-FIND("L",Data1!I51)),"Ø","0")," ","")) -> 72 | K54: =VALUE(SUBSTITUTE(SUBSTITUTE(RIGHT(Data1!J51,LEN(Data1!J51)-FIND("L",Data1!J51)),"Ø","0")," ","")) -> 71 | ... O54: =VALUE(SUBSTITUTE(SUBSTITUTE(RIGHT(Data1!N51,LEN(Data1!N51)-FIND("L",Data1!N51)),"Ø","0")," ","")) -> 36
B55: Lowest Tempeatures | D55: =MIN(D30:D54) -> 8 | E55: =MIN(E30:E54) -> 13 | F55: =MIN(F30:F54) -> 24 | G55: =MIN(G30:G54) -> 37 | H55: =MIN(H30:H54) -> 46 | I55: =MIN(I30:I54) -> 52 | J55: =MIN(J30:J54) -> 54 | K55: =MIN(K30:K54) -> 55 | ... O55: =MIN(O30:O54) -> 12
B57: Check Sum | D57: {=CheckSumLow} -> 172862 | E57: 185534 | F57: 214009 | G57: 248444 | H57: 287509 | I57: 323773 | J57: 343816 | K57: 340769 | L57: 312610 | M57: 266825 | N57: 222505 | O57: 182849

Sheet MonthSorted
J1: Workings
B2: Sorted Table of High Temperatures | J2: month
B3: For the Month of: | C3: Mar | J3: city | K3: high temp | L3: adjustment | M3: rank | N3: sort order
A4: Position | B4: City | C4: High Temperature
A5: {=CS_Int} -> 1 | B5: {=_xlfn.SORTBY(CHOOSE({1,2}, SummaryHigh!B5:B54, INDEX(SummaryHigh!D5:O54,,MATCH(C3, SummaryHigh!D4:O4,0))), INDEX(SummaryHigh!D5:O54,,MATCH(C3, SummaryHigh!D4:O4,0)), -1, SummaryHigh!B5:B54, 1)} -> Miami | C5: 80 | J5: =SummaryHigh!B5 -> Atlanta | K5: =VLOOKUP(J5,_xlfn.ANCHORARRAY($B$5),2,FALSE) -> 65 | L5: =K5-ROW()/1000 -> 64.995 | M5: =RANK(L5,$L$5:$L$54,0) -> 17 | N5: {=_xlfn.SORTBY(A5:A54, M5:M54, 1)} -> 24
A6: 2 | B6: Orlando | C6: 78 | J6: =SummaryHigh!B6 -> Austin | K6: =VLOOKUP(J6,_xlfn.ANCHORARRAY($B$5),2,FALSE) -> 72 | L6: =K6-ROW()/1000 -> 71.994 | M6: =RANK(L6,$L$5:$L$54,0) -> 9 | N6: 31
A7: 3 | B7: Phoenix | C7: 78 | J7: =SummaryHigh!B7 -> Baltimore | K7: =VLOOKUP(J7,_xlfn.ANCHORARRAY($B$5),2,FALSE) -> 54 | L7: =K7-ROW()/1000 -> 53.993 | M7: =RANK(L7,$L$5:$L$54,0) -> 33 | N7: 33
A8: 4 | B8: Tampa | C8: 76 | J8: =SummaryHigh!B8 -> Birmingham | K8: =VLOOKUP(J8,_xlfn.ANCHORARRAY($B$5),2,FALSE) -> 67 | L8: =K8-ROW()/1000 -> 66.992 | M8: =RANK(L8,$L$5:$L$54,0) -> 14 | N8: 49
A9: 5 | B9: Jacksonville | C9: 74 | J9: =SummaryHigh!B9 -> Boston | K9: =VLOOKUP(J9,_xlfn.ANCHORARRAY($B$5),2,FALSE) -> 45 | L9: =K9-ROW()/1000 -> 44.991 | M9: =RANK(L9,$L$5:$L$54,0) -> 46 | N9: 18
A10: 6 | B10: San Antonio | C10: 74 | J10: =SummaryHigh!B10 -> Buffalo | K10: =VLOOKUP(J10,_xlfn.ANCHORARRAY($B$5),2,FALSE) -> 42 | L10: =K10-ROW()/1000 -> 41.99 | M10: =RANK(L10,$L$5:$L$54,0) -> 48 | N10: 43
A11: 7 | B11: Houston | C11: 73 | J11: =SummaryHigh!B11 -> Charlotte | K11: =VLOOKUP(J11,_xlfn.ANCHORARRAY($B$5),2,FALSE) -> 63 | L11: =K11-ROW()/1000 -> 62.989 | M11: =RANK(L11,$L$5:$L$54,0) -> 20 | N11: 16
A12: 8 | B12: Riverside | C12: 73 | J12: =SummaryHigh!B12 -> Chicago | K12: =VLOOKUP(J12,_xlfn.ANCHORARRAY($B$5),2,FALSE) -> 47 | L12: =K12-ROW()/1000 -> 46.988 | M12: =RANK(L12,$L$5:$L$54,0) -> 43 | N12: 39
A13: 9 | B13: Austin | C13: 72 | J13: =SummaryHigh!B13 -> Cincinnati | K13: =VLOOKUP(J13,_xlfn.ANCHORARRAY($B$5),2,FALSE) -> 55 | L13: =K13-ROW()/1000 -> 54.987 | M13: =RANK(L13,$L$5:$L$54,0) -> 31 | N13: 2
A14: 10 | B14: New Orleans | C14: 72 | J14: =SummaryHigh!B14 -> Cleveland | K14: =VLOOKUP(J14,_xlfn.ANCHORARRAY($B$5),2,FALSE) -> 47 | L14: =K14-ROW()/1000 -> 46.986 | M14: =RANK(L14,$L$5:$L$54,0) -> 44 | N14: 28
A15: 11 | B15: Las Vegas | C15: 70 | J15: =SummaryHigh!B15 -> Columbus | K15: =VLOOKUP(J15,_xlfn.ANCHORARRAY($B$5),2,FALSE) -> 51 | L15: =K15-ROW()/1000 -> 50.985 | M15: =RANK(L15,$L$5:$L$54,0) -> 38 | N15: 20
A16: 12 | B16: Los Angeles | C16: 70 | J16: =SummaryHigh!B16 -> Dallas | K16: =VLOOKUP(J16,_xlfn.ANCHORARRAY($B$5),2,FALSE) -> 69 | L16: =K16-ROW()/1000 -> 68.984 | M16: =RANK(L16,$L$5:$L$54,0) -> 13 | N16: 21
A17: 13 | B17: Dallas | C17: 69 | J17: =SummaryHigh!B17 -> Denver | K17: =VLOOKUP(J17,_xlfn.ANCHORARRAY($B$5),2,FALSE) -> 54 | L17: =K17-ROW()/1000 -> 53.983 | M17: =RANK(L17,$L$5:$L$54,0) -> 34 | N17: 12
... A20: 16 | B20: San Jose | C20: 66 | J20: =SummaryHigh!B20 -> Houston | K20: =VLOOKUP(J20,_xlfn.ANCHORARRAY($B$5),2,FALSE) -> 73 | L20: =K20-ROW()/1000 -> 72.98 | M20: =RANK(L20,$L$5:$L$54,0) -> 7 | N20: 46
A21: 17 | B21: Atlanta | C21: 65 | J21: =SummaryHigh!B21 -> Indianapolis | K21: =VLOOKUP(J21,_xlfn.ANCHORARRAY($B$5),2,FALSE) -> 52 | L21: =K21-ROW()/1000 -> 51.979 | M21: =RANK(L21,$L$5:$L$54,0) -> 37 | N21: 1 | O21: =SUM(M24:M26) -> 49
A22: 18 | B22: Sacramento | C22: 65 | J22: =SummaryHigh!B22 -> Jacksonville | K22: =VLOOKUP(J22,_xlfn.ANCHORARRAY($B$5),2,FALSE) -> 74 | L22: =K22-ROW()/1000 -> 73.978 | M22: =RANK(L22,$L$5:$L$54,0) -> 5 | N22: 41
A23: 19 | B23: Memphis | C23: 64 | J23: =SummaryHigh!B23 -> Kansas City | K23: =VLOOKUP(J23,_xlfn.ANCHORARRAY($B$5),2,FALSE) -> 56 | L23: =K23-ROW()/1000 -> 55.977 | M23: =RANK(L23,$L$5:$L$54,0) -> 29 | N23: 23
A24: 20 | B24: Charlotte | C24: 63 | J24: =SummaryHigh!B24 -> Las Vegas | K24: =VLOOKUP(J24,_xlfn.ANCHORARRAY($B$5),2,FALSE) -> 70 | L24: =K24-ROW()/1000 -> 69.976 | M24: =RANK(L24,$L$5:$L$54,0) -> 11 | N24: 7 | O24: =SUM(N27:N39) -> 398
A25: 21 | B25: Oklahoma City | C25: 63 | J25: =SummaryHigh!B25 -> Los Angeles | K25: =VLOOKUP(J25,_xlfn.ANCHORARRAY($B$5),2,FALSE) -> 70 | L25: =K25-ROW()/1000 -> 69.975 | M25: =RANK(L25,$L$5:$L$54,0) -> 12 | N25: 30
A26: 22 | B26: Raleigh | C26: 63 | J26: =SummaryHigh!B26 -> Louisville | K26: =VLOOKUP(J26,_xlfn.ANCHORARRAY($B$5),2,FALSE) -> 58 | L26: =K26-ROW()/1000 -> 57.974 | M26: =RANK(L26,$L$5:$L$54,0) -> 26 | N26: 37
A27: 23 | B27: San Francisco | C27: 62 | J27: =SummaryHigh!B27 -> Memphis | K27: =VLOOKUP(J27,_xlfn.ANCHORARRAY($B$5),2,FALSE) -> 64 | L27: =K27-ROW()/1000 -> 63.973 | M27: =RANK(L27,$L$5:$L$54,0) -> 19 | N27: 45
A28: 24 | B28: Nashville | C28: 61 | J28: =SummaryHigh!B28 -> Miami | K28: =VLOOKUP(J28,_xlfn.ANCHORARRAY($B$5),2,FALSE) -> 80 | L28: =K28-ROW()/1000 -> 79.972 | M28: =RANK(L28,$L$5:$L$54,0) -> 1 | N28: 27
A29: 25 | B29: Richmond | C29: 60 | J29: =SummaryHigh!B29 -> Milwaukee | K29: =VLOOKUP(J29,_xlfn.ANCHORARRAY($B$5),2,FALSE) -> 42 | L29: =K29-ROW()/1000 -> 41.971 | M29: =RANK(L29,$L$5:$L$54,0) -> 49 | N29: 38
A30: 26 | B30: Louisville | C30: 58 | J30: =SummaryHigh!B30 -> Minneapolis | K30: =VLOOKUP(J30,_xlfn.ANCHORARRAY($B$5),2,FALSE) -> 41 | L30: =K30-ROW()/1000 -> 40.97 | M30: =RANK(L30,$L$5:$L$54,0) -> 50 | N30: 22
A31: 27 | B31: Virginia Beach | C31: 58 | J31: =SummaryHigh!B31 -> Nashville | K31: =VLOOKUP(J31,_xlfn.ANCHORARRAY($B$5),2,FALSE) -> 61 | L31: =K31-ROW()/1000 -> 60.969 | M31: =RANK(L31,$L$5:$L$54,0) -> 24 | N31: 50
A32: 28 | B32: Portland | C32: 57 | J32: =SummaryHigh!B32 -> New Orleans | K32: =VLOOKUP(J32,_xlfn.ANCHORARRAY($B$5),2,FALSE) -> 72 | L32: =K32-ROW()/1000 -> 71.968 | M32: =RANK(L32,$L$5:$L$54,0) -> 10 | N32: 35
A33: 29 | B33: Kansas City | C33: 56 | J33: =SummaryHigh!B33 -> New York | K33: =VLOOKUP(J33,_xlfn.ANCHORARRAY($B$5),2,FALSE) -> 50 | L33: =K33-ROW()/1000 -> 49.967 | M33: =RANK(L33,$L$5:$L$54,0) -> 39 | N33: 19
A34: 30 | B34: St. Louis | C34: 56 | J34: =SummaryHigh!B34 -> Oklahoma City | K34: =VLOOKUP(J34,_xlfn.ANCHORARRAY($B$5),2,FALSE) -> 63 | L34: =K34-ROW()/1000 -> 62.966 | M34: =RANK(L34,$L$5:$L$54,0) -> 21 | N34: 48
A35: 31 | B35: Cincinnati | C35: 55 | J35: =SummaryHigh!B35 -> Orlando | K35: =VLOOKUP(J35,_xlfn.ANCHORARRAY($B$5),2,FALSE) -> 78 | L35: =K35-ROW()/1000 -> 77.965 | M35: =RANK(L35,$L$5:$L$54,0) -> 2 | N35: 9
A36: 32 | B36: Seattle | C36: 55 | J36: =SummaryHigh!B36 -> Philadelphia | K36: =VLOOKUP(J36,_xlfn.ANCHORARRAY($B$5),2,FALSE) -> 53 | L36: =K36-ROW()/1000 -> 52.964 | M36: =RANK(L36,$L$5:$L$54,0) -> 36 | N36: 47
... A54: 50 | B54: Minneapolis | C54: 41 | J54: =SummaryHigh!B54 -> Virginia Beach | K54: =VLOOKUP(J54,_xlfn.ANCHORARRAY($B$5),2,FALSE) -> 58 | L54: =K54-ROW()/1000 -> 57.946 | M54: =RANK(L54,$L$5:$L$54,0) -> 27 | N54: 26
L55: =SUM(L5:L54) -> 2983.525
A56: Check Sum | B56: =CheckSumSortCity -> 382726 | C56: =CheckSumSortTemp -> 268583

Sheet Part 2
A1: This sheet is intentionally blank

Sheet Scenarios
B2: Part 2 - Introduction
B4: Your task is to calculate the future account balance of a savings account opened today with certain provided terms.
B5: Terms will be provided for Interest Rate, Number of Years and Additional Payments. There will also be an Initial Depsoit Amount.
B6: You will need to use these terms to look up the Initial Deposit Amount, and then calculate the future account balance.
B8: Interest Rate
B9: The account earns interest at one of the 6 following annual rates:
B10: 0.05
B11: 0.055
B12: 0.06
B13: 0.065
B14: 0.07
B15: 0.075
B16: Interest is paid into the account at the end of every 12 month period.
B18: Number of Years
B19: The account will be active for one of the following number of years, starting today:
B20: 4
B21: 5
B22: 6
B23: 7
B24: 8
B26: Additional Payments
B27: At the end of every 12 month period (beginning one year after today), an additional payment is deposited into the account.
B28: The additional payment will be one of the 4 following amounts:
B29: 1500
B30: 1800
B31: 2200
B32: 2700
B34: Initial Deposit
B35: When the account is opened today, an initial deposit is made into the account.
B36: The size of the deposit must be looked up from a table depending upon the chosen values for Interest Rate, Number of Years and Additional Payments.
B37: There is a table provided for each interest rate value (see worksheet "Rate_550" for the 5.50% rate for example).
B38: Each table has 20 initial deposit amounts, one for each combination of Years and Additional Payments.
B40: The amounts are located in cells C3:G6 of each table, with the rate in cell A1, the number of years in cells B2:G2 and the Additional Payment at cells B3:B6.
B42: Assumptions and Calculations
B44: Your task is to populate the green cells in the 'Initial Deposit' column and 'Final Account Balance' column for each of the 30 Account Numbers.
B45: Do your workings in the grey 'helper cells' box in columns I to X, so that the green cells contain only your final answers. Then answer the assignment questions.
B47: HINTS:
B48: 1) Try and write flexible formulas that can be copied down the entire column of 30 accounts. This will be the quickest way.
B49: 2) You may wish to use the INDIRECT function to find the Initial Deposit. Note that the Interest Rate * 10000 will give the number (500 to 750) that appears in the worksheet tab name.
B50: 3) You may wish to use the FV function to find the Final Account Balance. Make sure the Final Account Balance is a positive number.
I52: Helper cells if you need them
B53: Account Number | C53: Interest Rate | D53: Number of Years | E53: Additional Payments | F53: Initial Deposit | G53: Final Account Balance
B54: 1 | C54: 0.065 | D54: 4 | E54: 1500 | F54: =INDEX( INDIRECT("'Rate_" & TEXT(C54*10000,"000") & "'!C3:G6"), MATCH(E54, INDIRECT("'Rate_" & TEXT(C54*10000,"000") & "'!B3:B6"), 0), MATCH(D54, INDIRECT("'Rate_" & TEXT(C54*10000,"000") & "'!C2:G2"), 0) ) -> 5100 | G54: =FV(C54, D54,- E54, -F54, 0) -> 13171.74
B55: =B54+1 -> 2 | C55: 0.05 | D55: 6 | E55: 1800 | F55: =INDEX( INDIRECT("'Rate_" & TEXT(C55*10000,"000") & "'!C3:G6"), MATCH(E55, INDIRECT("'Rate_" & TEXT(C55*10000,"000") & "'!B3:B6"), 0), MATCH(D55, INDIRECT("'Rate_" & TEXT(C55*10000,"000") & "'!C2:G2"), 0) ) -> 7990 | G55: =FV(C55, D55,- E55, -F55, 0) -> 22950.807
B56: =B55+1 -> 3 | C56: 0.05 | D56: 7 | E56: 1500 | F56: =INDEX( INDIRECT("'Rate_" & TEXT(C56*10000,"000") & "'!C3:G6"), MATCH(E56, INDIRECT("'Rate_" & TEXT(C56*10000,"000") & "'!B3:B6"), 0), MATCH(D56, INDIRECT("'Rate_" & TEXT(C56*10000,"000") & "'!C2:G2"), 0) ) -> 5940 | G56: =FV(C56, D56,- E56, -F56, 0) -> 20571.189
B57: =B56+1 -> 4 | C57: 0.075 | D57: 7 | E57: 2200 | F57: =INDEX( INDIRECT("'Rate_" & TEXT(C57*10000,"000") & "'!C3:G6"), MATCH(E57, INDIRECT("'Rate_" & TEXT(C57*10000,"000") & "'!B3:B6"), 0), MATCH(D57, INDIRECT("'Rate_" & TEXT(C57*10000,"000") & "'!C2:G2"), 0) ) -> 6430 | G57: =FV(C57, D57,- E57, -F57, 0) -> 29999.794
B58: =B57+1 -> 5 | C58: 0.055 | D58: 6 | E58: 2200 | F58: =INDEX( INDIRECT("'Rate_" & TEXT(C58*10000,"000") & "'!C3:G6"), MATCH(E58, INDIRECT("'Rate_" & TEXT(C58*10000,"000") & "'!B3:B6"), 0), MATCH(D58, INDIRECT("'Rate_" & TEXT(C58*10000,"000") & "'!C2:G2"), 0) ) -> 7600 | G58: =FV(C58, D58,- E58, -F58, 0) -> 25632.918
B59: =B58+1 -> 6 | C59: 0.06 | D59: 7 | E59: 1500 | F59: =INDEX( INDIRECT("'Rate_" & TEXT(C59*10000,"000") & "'!C3:G6"), MATCH(E59, INDIRECT("'Rate_" & TEXT(C59*10000,"000") & "'!B3:B6"), 0), MATCH(D59, INDIRECT("'Rate_" & TEXT(C59*10000,"000") & "'!C2:G2"), 0) ) -> 5650 | G59: =FV(C59, D59,- E59, -F59, 0) -> 21086.267
B60: =B59+1 -> 7 | C60: 0.07 | D60: 6 | E60: 2700 | F60: =INDEX( INDIRECT("'Rate_" & TEXT(C60*10000,"000") & "'!C3:G6"), MATCH(E60, INDIRECT("'Rate_" & TEXT(C60*10000,"000") & "'!B3:B6"), 0), MATCH(D60, INDIRECT("'Rate_" & TEXT(C60*10000,"000") & "'!C2:G2"), 0) ) -> 6330 | G60: =FV(C60, D60,- E60, -F60, 0) -> 28813.508
B61: =B60+1 -> 8 | C61: 0.055 | D61: 5 | E61: 1800 | F61: =INDEX( INDIRECT("'Rate_" & TEXT(C61*10000,"000") & "'!C3:G6"), MATCH(E61, INDIRECT("'Rate_" & TEXT(C61*10000,"000") & "'!B3:B6"), 0), MATCH(D61, INDIRECT("'Rate_" & TEXT(C61*10000,"000") & "'!C2:G2"), 0) ) -> 6720 | G61: =FV(C61, D61,- E61, -F61, 0) -> 18828.735
B62: =B61+1 -> 9 | C62: 0.065 | D62: 4 | E62: 1800 | F62: =INDEX( INDIRECT("'Rate_" & TEXT(C62*10000,"000") & "'!C3:G6"), MATCH(E62, INDIRECT("'Rate_" & TEXT(C62*10000,"000") & "'!B3:B6"), 0), MATCH(D62, INDIRECT("'Rate_" & TEXT(C62*10000,"000") & "'!C2:G2"), 0) ) -> 6280 | G62: =FV(C62, D62,- E62, -F62, 0) -> 16011.923
B63: =B62+1 -> 10 | C63: 0.06 | D63: 5 | E63: 1800 | F63: =INDEX( INDIRECT("'Rate_" & TEXT(C63*10000,"000") & "'!C3:G6"), MATCH(E63, INDIRECT("'Rate_" & TEXT(C63*10000,"000") & "'!B3:B6"), 0), MATCH(D63, INDIRECT("'Rate_" & TEXT(C63*10000,"000") & "'!C2:G2"), 0) ) -> 6200 | G63: =FV(C63, D63,- E63, -F63, 0) -> 18443.766
B64: =B63+1 -> 11 | C64: 0.06 | D64: 4 | E64: 1500 | F64: =INDEX( INDIRECT("'Rate_" & TEXT(C64*10000,"000") & "'!C3:G6"), MATCH(E64, INDIRECT("'Rate_" & TEXT(C64*10000,"000") & "'!B3:B6"), 0), MATCH(D64, INDIRECT("'Rate_" & TEXT(C64*10000,"000") & "'!C2:G2"), 0) ) -> 5260 | G64: =FV(C64, D64,- E64, -F64, 0) -> 13202.553
B65: =B64+1 -> 12 | C65: 0.065 | D65: 4 | E65: 2200 | F65: =INDEX( INDIRECT("'Rate_" & TEXT(C65*10000,"000") & "'!C3:G6"), MATCH(E65, INDIRECT("'Rate_" & TEXT(C65*10000,"000") & "'!B3:B6"), 0), MATCH(D65, INDIRECT("'Rate_" & TEXT(C65*10000,"000") & "'!C2:G2"), 0) ) -> 7240 | G65: =FV(C65, D65,- E65, -F65, 0) -> 19009.801
B66: =B65+1 -> 13 | C66: 0.07 | D66: 6 | E66: 2200 | F66: =INDEX( INDIRECT("'Rate_" & TEXT(C66*10000,"000") & "'!C3:G6"), MATCH(E66, INDIRECT("'Rate_" & TEXT(C66*10000,"000") & "'!B3:B6"), 0), MATCH(D66, INDIRECT("'Rate_" & TEXT(C66*10000,"000") & "'!C2:G2"), 0) ) -> 5130 | G66: =FV(C66, D66,- E66, -F66, 0) -> 23435.986
... B83: =B82+1 -> 30 | C83: 0.065 | D83: 5 | E83: 2200 | F83: =INDEX( INDIRECT("'Rate_" & TEXT(C83*10000,"000") & "'!C3:G6"), MATCH(E83, INDIRECT("'Rate_" & TEXT(C83*10000,"000") & "'!B3:B6"), 0), MATCH(D83, INDIRECT("'Rate_" & TEXT(C83*10000,"000") & "'!C2:G2"), 0) ) -> 7490 | G83: =FV(C83, D83,- E83, -F83, 0) -> 22787.959
E85: Check Sum | F85: =SUM(F54:F83) -> 196830 | G85: =SUM(G54:G83) -> 713101.1
B88: End of Sheet

Sheet Rate_500
A1: 0.05 | B1: <-- Rate | C1: Number of Years (Across Top Row)
B2: Purchase Price (PV) in middle | C2: 4 | D2: 5 | E2: 6 | F2: 7 | G2: 8
A3: Pmt per Year | B3: 1500 | C3: 5530 | D3: 7840 | E3: 7440 | F3: 5940 | G3: 7510
A4: (Down | B4: 1800 | C4: 5850 | D4: 6160 | E4: 7990 | F4: 7300 | G4: 7110
A5: Left | B5: 2200 | C5: 5270 | D5: 7900 | E5: 6250 | F5: 5750 | G5: 6070
A6: Column) | B6: 2700 | C6: 6950 | D6: 5860 | E6: 7420 | F6: 7930 | G6: 6170

Sheet Rate_550
A1: 0.055 | B1: <-- Rate | C1: Number of Years (Across Top Row)
B2: Purchase Price (PV) in middle | C2: 4 | D2: 5 | E2: 6 | F2: 7 | G2: 8
A3: Pmt per Year | B3: 1500 | C3: 7620 | D3: 7540 | E3: 6660 | F3: 6120 | G3: 7520
A4: (Down | B4: 1800 | C4: 5940 | D4: 6720 | E4: 7720 | F4: 6860 | G4: 7210
A5: Left | B5: 2200 | C5: 6060 | D5: 7930 | E5: 7600 | F5: 5940 | G5: 5980
A6: Column) | B6: 2700 | C6: 6430 | D6: 5960 | E6: 6400 | F6: 5560 | G6: 5810

Sheet Rate_600
A1: 0.06 | B1: <-- Rate | C1: Number of Years (Across Top Row)
B2: Purchase Price (PV) in middle | C2: 4 | D2: 5 | E2: 6 | F2: 7 | G2: 8
A3: Pmt per Year | B3: 1500 | C3: 5260 | D3: 6350 | E3: 6810 | F3: 5650 | G3: 6970
A4: (Down | B4: 1800 | C4: 7860 | D4: 6200 | E4: 5820 | F4: 5870 | G4: 5200
A5: Left | B5: 2200 | C5: 7730 | D5: 6240 | E5: 6980 | F5: 5920 | G5: 5190
A6: Column) | B6: 2700 | C6: 5120 | D6: 5040 | E6: 7440 | F6: 5640 | G6: 5740

Sheet Rate_650
A1: 0.065 | B1: <-- Rate | C1: Number of Years (Across Top Row)
B2: Purchase Price (PV) in middle | C2: 4 | D2: 5 | E2: 6 | F2: 7 | G2: 8
A3: Pmt per Year | B3: 1500 | C3: 5100 | D3: 6270 | E3: 6700 | F3: 6410 | G3: 7600
A4: (Down | B4: 1800 | C4: 6280 | D4: 6110 | E4: 7600 | F4: 6740 | G4: 6090
A5: Left | B5: 2200 | C5: 7240 | D5: 7490 | E5: 5130 | F5: 6240 | G5: 5910
A6: Column) | B6: 2700 | C6: 7940 | D6: 5960 | E6: 5450 | F6: 7070 | G6: 6870

Sheet Rate_700
A1: 0.07 | B1: <-- Rate | C1: Number of Years (Across Top Row)
B2: Purchase Price (PV) in middle | C2: 4 | D2: 5 | E2: 6 | F2: 7 | G2: 8
A3: Pmt per Year | B3: 1500 | C3: 6150 | D3: 7690 | E3: 6230 | F3: 6440 | G3: 7160
A4: (Down | B4: 1800 | C4: 7350 | D4: 5030 | E4: 7780 | F4: 6250 | G4: 6690
A5: Left | B5: 2200 | C5: 5610 | D5: 7680 | E5: 5130 | F5: 7260 | G5: 7350
A6: Column) | B6: 2700 | C6: 6550 | D6: 5380 | E6: 6330 | F6: 7020 | G6: 6920

Sheet Rate_750
A1: 0.075 | B1: <-- Rate | C1: Number of Years (Across Top Row)
B2: Purchase Price (PV) in middle | C2: 4 | D2: 5 | E2: 6 | F2: 7 | G2: 8
A3: Pmt per Year | B3: 1500 | C3: 6240 | D3: 5320 | E3: 7500 | F3: 5770 | G3: 5220
A4: (Down | B4: 1800 | C4: 5950 | D4: 7680 | E4: 5450 | F4: 5500 | G4: 6120
A5: Left | B5: 2200 | C5: 7420 | D5: 6480 | E5: 5480 | F5: 6430 | G5: 5480
A6: Column) | B6: 2700 | C6: 7020 | D6: 7590 | E6: 5280 | F6: 5240 | G6: 6560
