Workbook
Name Model_Start_Date: Inputs!$F$14
Name Raw: [1]Raw!$B$3:$F$54
Name Towns: [1]Distances!$B$4:$B$8

Sheet Introduction
H2: Excel Skills for Business: Advanced
H4: Week 1: Spreadsheet Design and Documentation
I6: Final Assessment
A10: Week 1: Learning Objectives
B12: Use the following functionalities in Excel for Spreadsheet Design and Documentation: Design flexible and auditable spreadsheets Build robust and transparent calculations Create self-documenting spreadsheets Use formatting to enhance functionality

Sheet Inputs
B3: Formatting Legend
C5: User-variable assumption | F5: 1000 | G5: =Model_Start_Date -> 43101 | H5: =G6+1 -> 43132 | I5: =H6+1 -> 43160 | J5: =I6+1 -> 43191 | K5: =J6+1 -> 43221 | L5: =K6+1 -> 43252 | M5: =L6+1 -> 43282 | N5: =M6+1 -> 43313 | O5: =N6+1 -> 43344 | ... BN5: =BM6+1 -> 44896
C6: Fixed assumption | F6: 1000 | G6: =EOMONTH(G5, 0) -> 43131 | H6: =EOMONTH(H5, 0) -> 43159 | I6: =EOMONTH(I5, 0) -> 43190 | J6: =EOMONTH(J5, 0) -> 43220 | K6: =EOMONTH(K5, 0) -> 43251 | L6: =EOMONTH(L5, 0) -> 43281 | M6: =EOMONTH(M5, 0) -> 43312 | N6: =EOMONTH(N5, 0) -> 43343 | ... BN6: =EOMONTH(BN5, 0) -> 44926
C7: Calculation | F7: 1000 | G7: =MONTH(G5) -> 1 | H7: =MONTH(H5) -> 2 | I7: =MONTH(I5) -> 3 | J7: =MONTH(J5) -> 4 | K7: =MONTH(K5) -> 5 | L7: =MONTH(L5) -> 6 | M7: =MONTH(M5) -> 7 | N7: =MONTH(N5) -> 8 | ... BN7: =MONTH(BN5) -> 12
C8: Unique Calculation | F8: 1000 | G8: =YEAR(G5) -> 2018 | H8: =YEAR(H5) -> 2018 | I8: =YEAR(I5) -> 2018 | J8: =YEAR(J5) -> 2018 | K8: =YEAR(K5) -> 2018 | L8: =YEAR(L5) -> 2018 | M8: =YEAR(M5) -> 2018 | N8: =YEAR(N5) -> 2018 | ... BN8: =YEAR(BN5) -> 2022
C9: Units label | F9: [$]
B11: Assumptions | F11: 1 | G11: =F11*(1+IF(G$7=Inputs!$F$32,INDEX(Inputs!$F$26:$F$30,MATCH(G$8,Inputs!$E$26:$E$30,0)),0)) -> 1 | H11: =G11*(1+IF(H$7=Inputs!$F$32,INDEX(Inputs!$F$26:$F$30,MATCH(H$8,Inputs!$E$26:$E$30,0)),0)) -> 1 | I11: =H11*(1+IF(I$7=Inputs!$F$32,INDEX(Inputs!$F$26:$F$30,MATCH(I$8,Inputs!$E$26:$E$30,0)),0)) -> 1 | J11: =I11*(1+IF(J$7=Inputs!$F$32,INDEX(Inputs!$F$26:$F$30,MATCH(J$8,Inputs!$E$26:$E$30,0)),0)) -> 1 | K11: =J11*(1+IF(K$7=Inputs!$F$32,INDEX(Inputs!$F$26:$F$30,MATCH(K$8,Inputs!$E$26:$E$30,0)),0)) -> 1 | L11: =K11*(1+IF(L$7=Inputs!$F$32,INDEX(Inputs!$F$26:$F$30,MATCH(L$8,Inputs!$E$26:$E$30,0)),0)) -> 1 | M11: =L11*(1+IF(M$7=Inputs!$F$32,INDEX(Inputs!$F$26:$F$30,MATCH(M$8,Inputs!$E$26:$E$30,0)),0)) -> 1.05 | N11: =M11*(1+IF(N$7=Inputs!$F$32,INDEX(Inputs!$F$26:$F$30,MATCH(N$8,Inputs!$E$26:$E$30,0)),0)) -> 1.05 | ... BN11: =BM11*(1+IF(BN$7=Inputs!$F$32,INDEX(Inputs!$F$26:$F$30,MATCH(BN$8,Inputs!$E$26:$E$30,0)),0)) -> 1.2032897
F12: 1 | G12: =F12*(1+IF(G$7=Inputs!$F$42,INDEX(Inputs!$F$36:$F$40,MATCH(G$8,Inputs!$E$36:$E$40,0)),0)) -> 1 | H12: =G12*(1+IF(H$7=Inputs!$F$42,INDEX(Inputs!$F$36:$F$40,MATCH(H$8,Inputs!$E$36:$E$40,0)),0)) -> 1 | I12: =H12*(1+IF(I$7=Inputs!$F$42,INDEX(Inputs!$F$36:$F$40,MATCH(I$8,Inputs!$E$36:$E$40,0)),0)) -> 1 | J12: =I12*(1+IF(J$7=Inputs!$F$42,INDEX(Inputs!$F$36:$F$40,MATCH(J$8,Inputs!$E$36:$E$40,0)),0)) -> 1.03 | K12: =J12*(1+IF(K$7=Inputs!$F$42,INDEX(Inputs!$F$36:$F$40,MATCH(K$8,Inputs!$E$36:$E$40,0)),0)) -> 1.03 | L12: =K12*(1+IF(L$7=Inputs!$F$42,INDEX(Inputs!$F$36:$F$40,MATCH(L$8,Inputs!$E$36:$E$40,0)),0)) -> 1.03 | M12: =L12*(1+IF(M$7=Inputs!$F$42,INDEX(Inputs!$F$36:$F$40,MATCH(M$8,Inputs!$E$36:$E$40,0)),0)) -> 1.03 | N12: =M12*(1+IF(N$7=Inputs!$F$42,INDEX(Inputs!$F$36:$F$40,MATCH(N$8,Inputs!$E$36:$E$40,0)),0)) -> 1.03 | ... BN12: =BM12*(1+IF(BN$7=Inputs!$F$42,INDEX(Inputs!$F$36:$F$40,MATCH(BN$8,Inputs!$E$36:$E$40,0)),0)) -> 1.2048429
B13: General
C14: Model Start Date | F14: 43101
C15: Monthly periods modelled | F15: 60
C16: End Date of Model | E16: =SUM(G16:BN16) -> 5022768.9 | F16: =EOMONTH(F14,F15-1) -> 44926 | G16: =$F$19*G11 -> 75000 | H16: =$F$19*H11 -> 75000 | I16: =$F$19*I11 -> 75000 | J16: =$F$19*J11 -> 75000 | K16: =$F$19*K11 -> 75000 | L16: =$F$19*L11 -> 75000 | M16: =$F$19*M11 -> 78750 | N16: =$F$19*N11 -> 78750 | ... BN16: =$F$19*BN11 -> 90246.728
G17: =$F$20*G16 -> 48750 | H17: =$F$20*H16 -> 48750 | I17: =$F$20*I16 -> 48750 | J17: =$F$20*J16 -> 48750 | K17: =$F$20*K16 -> 48750 | L17: =$F$20*L16 -> 48750 | M17: =$F$20*M16 -> 51187.5 | N17: =$F$20*N16 -> 51187.5 | ... BN17: =$F$20*BN16 -> 58660.373
B18: Initial values | F18: Gross Margin | G18: =G16-G17 -> 26250 | H18: =H16-H17 -> 26250 | I18: =I16-I17 -> 26250 | J18: =J16-J17 -> 26250 | K18: =K16-K17 -> 26250 | L18: =L16-L17 -> 26250 | M18: =M16-M17 -> 27562.5 | N18: =N16-N17 -> 27562.5 | ... BN18: =BN16-BN17 -> 31586.355
C19: Revenues | D19: [$ / month] | F19: 75000
C20: Cost of Goods Sold | D20: [% of Revenue] | E20: =SUM(G20:BN20) -> 799105.33 | F20: 0.65 | G20: =$F$21*G12 -> 12000 | H20: =$F$21*H12 -> 12000 | I20: =$F$21*I12 -> 12000 | J20: =$F$21*J12 -> 12360 | K20: =$F$21*K12 -> 12360 | L20: =$F$21*L12 -> 12360 | M20: =$F$21*M12 -> 12360 | N20: =$F$21*N12 -> 12360 | ... BN20: =$F$21*BN12 -> 14458.115
C21: Expenses | D21: [$ / month] | F21: 12000
F22: Net Income | G22: =G18-G20 -> 14250 | H22: =H18-H20 -> 14250 | I22: =I18-I20 -> 14250 | J22: =J18-J20 -> 13890 | K22: =K18-K20 -> 13890 | L22: =L18-L20 -> 13890 | M22: =M18-M20 -> 15202.5 | N22: =N18-N20 -> 15202.5 | ... AH22: =AH18-AH20 -> 15223.005
B24: Growth Rates
C25: Revenues | E25: Year | F25: % Growth
E26: =YEAR(F14) -> 2018 | F26: 0.05
E27: =E26+1 -> 2019 | F27: 0.042
E28: =E27+1 -> 2020 | F28: 0.0613
E29: =E28+1 -> 2021 | F29: 0.011
E30: =E29+1 -> 2022 | F30: 0.025
C32: Growth occurs on first day of which month number: | F32: 7
C33: (1 = January, 12 = December etc)
C35: Expenses | E35: Year | F35: % Growth
E36: =E26 -> 2018 | F36: 0.03
E37: =E27 -> 2019 | F37: 0.04
E38: =E28 -> 2020 | F38: 0.05
E39: =E29 -> 2021 | F39: 0.04
E40: =E30 -> 2022 | F40: 0.03
C42: Growth occurs on first day of which month number: | F42: 4
C43: (1 = January, 12 = December etc)
B45: End of Sheet
